[
{"category": "Points", "place": 1, "player_name": "Keegan Murray", "team_name": "SAC", "stat": 25},
{"category": "Points", "place": 2, "player_name": "Jaylen Brown", "team_name": "BOS", "stat": 20},
{"category": "Points", "place": 2, "player_name": "Domantas Sabonis", "team_name": "SAC", "stat": 20},
{"category": "Points", "place": 4, "player_name": "Bojan Bogdanovic", "team_name": "DET", "stat": 17},
{"category": "Points", "place": 5, "player_name": "Miles Bridges", "team_name": "CHA", "stat": 16},
{"category": "Rebounds", "place": 1, "player_name": "Victor Wembanyama", "team_name": "SAS", "stat": 11},
{"category": "Rebounds", "place": 2, "player_name": "Domantas Sabonis", "team_name": "SAC", "stat": 9},
{"category": "Rebounds", "place": 3, "player_name": "Karl-Anthony Towns", "team_name": "MIN", "stat": 8},
{"category": "Rebounds", "place": 4, "player_name": "Kyle Kuzma", "team_name": "WAS", "stat": 7},
{"category": "Rebounds", "place": 4, "player_name": "Naz Reid", "team_name": "MIN", "stat": 7},
{"category": "Assists", "place": 1, "player_name": "Killian Hayes", "team_name": "DET", "stat": 7},
{"category": "Assists", "place": 1, "player_name": "Domantas Sabonis", "team_name": "SAC", "stat": 7},
{"category": "Assists", "place": 3, "player_name": "Bruce Brown", "team_name": "IND", "stat": 6},
{"category": "Assists", "place": 3, "player_name": "Victor Wembanyama", "team_name": "SAS", "stat": 6},
{"category": "Assists", "place": 5, "player_name": "Kyle Anderson", "team_name": "MIN", "stat": 5},
{"category": "Blocks", "place": 1, "player_name": "Daniel Gafford", "team_name": "WAS", "stat": 3},
{"category": "Blocks", "place": 2, "player_name": "Mo Bamba", "team_name": "PHI", "stat": 1},
{"category": "Blocks", "place": 2, "player_name": "Dominick Barlow", "team_name": "SAS", "stat": 1},
{"category": "Blocks", "place": 2, "player_name": "Bilal Coulibaly", "team_name": "WAS", "stat": 1},
{"category": "Blocks", "place": 2, "player_name": "Bruno Fernando", "team_name": "ATL", "stat": 1},
{"category": "Steals", "place": 1, "player_name": "Bogdan Bogdanovic", "team_name": "ATL", "stat": 2},
{"category": "Steals", "place": 1, "player_name": "Kyle Kuzma", "team_name": "WAS", "stat": 2},
{"category": "Steals", "place": 1, "player_name": "T.J. McConnell", "team_name": "IND", "stat": 2},
{"category": "Steals", "place": 1, "player_name": "Andrew Nembhard", "team_name": "IND", "stat": 2},
{"category": "Steals", "place": 1, "player_name": "Jordan Poole", "team_name": "WAS", "stat": 2},
{"category": "Turnovers", "place": 1, "player_name": "Andrew Nembhard", "team_name": "IND", "stat": 4},
{"category": "Turnovers", "place": 2, "player_name": "Miles Bridges", "team_name": "CHA", "stat": 2},
{"category": "Turnovers", "place": 2, "player_name": "Daniel Gafford", "team_name": "WAS", "stat": 2},
{"category": "Turnovers", "place": 2, "player_name": "Tre Jones", "team_name": "SAS", "stat": 2},
{"category": "Turnovers", "place": 2, "player_name": "Tyus Jones", "team_name": "WAS", "stat": 2},
{"category": "Three Pointers Made", "place": 1, "player_name": "Jaylen Brown", "team_name": "BOS", "stat": 4},
{"category": "Three Pointers Made", "place": 2, "player_name": "Bojan Bogdanovic", "team_name": "DET", "stat": 3},
{"category": "Three Pointers Made", "place": 2, "player_name": "De'Aaron Fox", "team_name": "SAC", "stat": 3},
{"category": "Three Pointers Made", "place": 2, "player_name": "Corey Kispert", "team_name": "WAS", "stat": 3},
{"category": "Three Pointers Made", "place": 2, "player_name": "Marcus Morris Sr.", "team_name": "PHI", "stat": 3},
{"category": "Free Throws Made", "place": 1, "player_name": "Jayson Tatum", "team_name": "BOS", "stat": 6},
{"category": "Free Throws Made", "place": 1, "player_name": "Karl-Anthony Towns", "team_name": "MIN", "stat": 6},
{"category": "Free Throws Made", "place": 3, "player_name": "Onyeka Okongwu", "team_name": "ATL", "stat": 5},
{"category": "Free Throws Made", "place": 3, "player_name": "Domantas Sabonis", "team_name": "SAC", "stat": 5},
{"category": "Free Throws Made", "place": 5, "player_name": "Bennedict Mathurin", "team_name": "IND", "stat": 4},
{"category": "Fantasy Points", "place": 1, "player_name": "Domantas Sabonis", "team_name": "SAC", "stat": 43.3},
{"category": "Fantasy Points", "place": 2, "player_name": "Keegan Murray", "team_name": "SAC", "stat": 39.7},
{"category": "Fantasy Points", "place": 3, "player_name": "Victor Wembanyama", "team_name": "SAS", "stat": 39.2},
{"category": "Fantasy Points", "place": 4, "player_name": "Karl-Anthony Towns", "team_name": "MIN", "stat": 34.1},
{"category": "Fantasy Points", "place": 5, "player_name": "Miles Bridges", "team_name": "CHA", "stat": 28.7}
]