[
{"category": "Assists", "place": 1, "player_name": "Anthony Edwards", "team_name": "MIN", "stat": 9, "player_link": "https://www.nba.com/stats/player/1630162/", "photo": "https://cdn.nba.com/headshots/nba/latest/1040x760/1630162.png", "ppg": "29.2", "rpg": "5.1", "apg": "3.8", "pie": "--", "team_logo": "https://cdn.nba.com/logos/nba/1610612750/primary/D/logo.svg"},
{"category": "Rebounds", "place": 5, "player_name": "Jarrett Allen", "team_name": "CLE", "stat": 10, "player_link": "https://www.nba.com/stats/player/1628386/", "photo": "https://cdn.nba.com/headshots/nba/latest/1040x760/1628386.png", "ppg": "13.8", "rpg": "8.0", "apg": "2.1", "pie": "--", "team_logo": "https://cdn.nba.com/logos/nba/1610612739/primary/L/logo.svg"},
{"category": "Rebounds", "place": 3, "player_name": "Julius Randle", "team_name": "MIN", "stat": 11, "player_link": "https://www.nba.com/stats/player/203944/", "photo": "https://cdn.nba.com/headshots/nba/latest/1040x760/203944.png", "ppg": "22.3", "rpg": "7.2", "apg": "5.8", "pie": "--", "team_logo": "https://cdn.nba.com/logos/nba/1610612750/primary/D/logo.svg"},
{"category": "Rebounds", "place": 3, "player_name": "Anthony Davis", "team_name": "DAL", "stat": 11, "player_link": "https://www.nba.com/stats/player/203076/", "photo": "https://cdn.nba.com/headshots/nba/latest/1040x760/203076.png", "ppg": "20.4", "rpg": "11.1", "apg": "2.8", "pie": "--", "team_logo": "https://cdn.nba.com/logos/nba/1610612742/primary/D/logo.svg"},
{"category": "Rebounds", "place": 2, "player_name": "Rudy Gobert", "team_name": "MIN", "stat": 13, "player_link": "https://www.nba.com/stats/player/203497/", "photo": "https://cdn.nba.com/headshots/nba/latest/1040x760/203497.png", "ppg": "11.3", "rpg": "11.3", "apg": "1.8", "pie": "--", "team_logo": "https://cdn.nba.com/logos/nba/1610612750/primary/D/logo.svg"},
{"category": "Rebounds", "place": 1, "player_name": "Pascal Siakam", "team_name": "IND", "stat": 14, "player_link": "https://www.nba.com/stats/player/1627783/", "photo": "https://cdn.nba.com/headshots/nba/latest/1040x760/1627783.png", "ppg": "23.9", "rpg": "6.8", "apg": "3.8", "pie": "--", "team_logo": "https://cdn.nba.com/logos/nba/1610612754/primary/D/logo.svg"},
{"category": "Points", "place": 5, "player_name": "Julius Randle", "team_name": "MIN", "stat": 28, "player_link": "https://www.nba.com/stats/player/203944/", "photo": "https://cdn.nba.com/headshots/nba/latest/1040x760/203944.png", "ppg": "22.3", "rpg": "7.2", "apg": "5.8", "pie": "--", "team_logo": "https://cdn.nba.com/logos/nba/1610612750/primary/D/logo.svg"},
{"category": "Points", "place": 3, "player_name": "Pascal Siakam", "team_name": "IND", "stat": 30, "player_link": "https://www.nba.com/stats/player/1627783/", "photo": "https://cdn.nba.com/headshots/nba/latest/1040x760/1627783.png", "ppg": "23.9", "rpg": "6.8", "apg": "3.8", "pie": "--", "team_logo": "https://cdn.nba.com/logos/nba/1610612754/primary/D/logo.svg"},
{"category": "Points", "place": 3, "player_name": "Donovan Mitchell", "team_name": "CLE", "stat": 30, "player_link": "https://www.nba.com/stats/player/1628378/", "photo": "https://cdn.nba.com/headshots/nba/latest/1040x760/1628378.png", "ppg": "29.8", "rpg": "4.8", "apg": "5.5", "pie": "--", "team_logo": "https://cdn.nba.com/logos/nba/1610612739/primary/L/logo.svg"},
{"category": "Points", "place": 1, "player_name": "LaMelo Ball", "team_name": "CHA", "stat": 33, "player_link": "https://www.nba.com/stats/player/1630163/", "photo": "https://cdn.nba.com/headshots/nba/latest/1040x760/1630163.png", "ppg": "20.0", "rpg": "5.0", "apg": "7.9", "pie": "--", "team_logo": "https://cdn.nba.com/logos/nba/1610612766/primary/D/logo.svg"},
{"category": "Points", "place": 1, "player_name": "Lauri Markkanen", "team_name": "UTA", "stat": 33, "player_link": "https://www.nba.com/stats/player/1628374/", "photo": "https://cdn.nba.com/headshots/nba/latest/1040x760/1628374.png", "ppg": "27.9", "rpg": "7.0", "apg": "2.2", "pie": "--", "team_logo": "https://cdn.nba.com/logos/nba/1610612762/primary/D/logo.svg"},
{"category": "Free Throws Made", "place": 2, "player_name": "Kon Knueppel", "team_name": "CHA", "stat": 6, "player_link": "https://www.nba.com/stats/player/1642851/", "photo": "https://cdn.nba.com/headshots/nba/latest/1040x760/1642851.png", "ppg": "19.3", "rpg": "5.2", "apg": "3.5", "pie": "--", "team_logo": "https://cdn.nba.com/logos/nba/1610612766/primary/D/logo.svg"},
{"category": "Free Throws Made", "place": 2, "player_name": "Moussa Diabaté", "team_name": "CHA", "stat": 6, "player_link": "https://www.nba.com/stats/player/1631217/", "photo": "https://cdn.nba.com/headshots/nba/latest/1040x760/1631217.png", "ppg": "8.0", "rpg": "8.2", "apg": "1.4", "pie": "--", "team_logo": "https://cdn.nba.com/logos/nba/1610612766/primary/D/logo.svg"},
{"category": "Free Throws Made", "place": 1, "player_name": "Donovan Mitchell", "team_name": "CLE", "stat": 8, "player_link": "https://www.nba.com/stats/player/1628378/", "photo": "https://cdn.nba.com/headshots/nba/latest/1040x760/1628378.png", "ppg": "29.8", "rpg": "4.8", "apg": "5.5", "pie": "--", "team_logo": "https://cdn.nba.com/logos/nba/1610612739/primary/L/logo.svg"},
{"category": "Three Pointers Made", "place": 5, "player_name": "Walter Clayton Jr.", "team_name": "UTA", "stat": 4, "player_link": "https://www.nba.com/stats/player/1642383/", "photo": "https://cdn.nba.com/headshots/nba/latest/1040x760/1642383.png", "ppg": "7.0", "rpg": "2.0", "apg": "3.1", "pie": "--", "team_logo": "https://cdn.nba.com/logos/nba/1610612762/primary/D/logo.svg"},
{"category": "Three Pointers Made", "place": 4, "player_name": "Sam Merrill", "team_name": "CLE", "stat": 5, "player_link": "https://www.nba.com/stats/player/1630241/", "photo": "https://cdn.nba.com/headshots/nba/latest/1040x760/1630241.png", "ppg": "14.0", "rpg": "2.4", "apg": "2.5", "pie": "--", "team_logo": "https://cdn.nba.com/logos/nba/1610612739/primary/L/logo.svg"},
{"category": "Fantasy Points", "place": 5, "player_name": "Julius Randle", "team_name": "MIN", "stat": 49.2, "player_link": "https://www.nba.com/stats/player/203944/", "photo": "https://cdn.nba.com/headshots/nba/latest/1040x760/203944.png", "ppg": "22.3", "rpg": "7.2", "apg": "5.8", "pie": "--", "team_logo": "https://cdn.nba.com/logos/nba/1610612750/primary/D/logo.svg"},
{"category": "Fantasy Points", "place": 4, "player_name": "Donovan Mitchell", "team_name": "CLE", "stat": 49.4, "player_link": "https://www.nba.com/stats/player/1628378/", "photo": "https://cdn.nba.com/headshots/nba/latest/1040x760/1628378.png", "ppg": "29.8", "rpg": "4.8", "apg": "5.5", "pie": "--", "team_logo": "https://cdn.nba.com/logos/nba/1610612739/primary/L/logo.svg"},
{"category": "Fantasy Points", "place": 3, "player_name": "Lauri Markkanen", "team_name": "UTA", "stat": 50.4, "player_link": "https://www.nba.com/stats/player/1628374/", "photo": "https://cdn.nba.com/headshots/nba/latest/1040x760/1628374.png", "ppg": "27.9", "rpg": "7.0", "apg": "2.2", "pie": "--", "team_logo": "https://cdn.nba.com/logos/nba/1610612762/primary/D/logo.svg"},
{"category": "Fantasy Points", "place": 2, "player_name": "LaMelo Ball", "team_name": "CHA", "stat": 54.6, "player_link": "https://www.nba.com/stats/player/1630163/", "photo": "https://cdn.nba.com/headshots/nba/latest/1040x760/1630163.png", "ppg": "20.0", "rpg": "5.0", "apg": "7.9", "pie": "--", "team_logo": "https://cdn.nba.com/logos/nba/1610612766/primary/D/logo.svg"},
{"category": "Fantasy Points", "place": 1, "player_name": "Cooper Flagg", "team_name": "DAL", "stat": 59.0, "player_link": "https://www.nba.com/stats/player/1642843/", "photo": "https://cdn.nba.com/headshots/nba/latest/1040x760/1642843.png", "ppg": "19.1", "rpg": "6.6", "apg": "4.3", "pie": "--", "team_logo": "https://cdn.nba.com/logos/nba/1610612742/primary/D/logo.svg"},
{"category": "Free Throws Made", "place": 5, "player_name": "Johnny Furphy", "team_name": "IND", "stat": 4, "player_link": "https://www.nba.com/stats/player/1642277/", "photo": "https://cdn.nba.com/headshots/nba/latest/1040x760/1642277.png", "ppg": "4.9", "rpg": "3.3", "apg": "0.6", "pie": "--", "team_logo": "https://cdn.nba.com/logos/nba/1610612754/primary/D/logo.svg"},
{"category": "Free Throws Made", "place": 4, "player_name": "Julius Randle", "team_name": "MIN", "stat": 5, "player_link": "https://www.nba.com/stats/player/203944/", "photo": "https://cdn.nba.com/headshots/nba/latest/1040x760/203944.png", "ppg": "22.3", "rpg": "7.2", "apg": "5.8", "pie": "--", "team_logo": "https://cdn.nba.com/logos/nba/1610612750/primary/D/logo.svg"},
{"category": "Three Pointers Made", "place": 2, "player_name": "Klay Thompson", "team_name": "DAL", "stat": 6, "player_link": "https://www.nba.com/stats/player/202691/", "photo": "https://cdn.nba.com/headshots/nba/latest/1040x760/202691.png", "ppg": "11.3", "rpg": "2.5", "apg": "1.3", "pie": "--", "team_logo": "https://cdn.nba.com/logos/nba/1610612742/primary/D/logo.svg"},
{"category": "Three Pointers Made", "place": 2, "player_name": "Donte DiVincenzo", "team_name": "MIN", "stat": 6, "player_link": "https://www.nba.com/stats/player/1628978/", "photo": "https://cdn.nba.com/headshots/nba/latest/1040x760/1628978.png", "ppg": "13.2", "rpg": "4.4", "apg": "4.0", "pie": "--", "team_logo": "https://cdn.nba.com/logos/nba/1610612750/primary/D/logo.svg"},
{"category": "Three Pointers Made", "place": 1, "player_name": "LaMelo Ball", "team_name": "CHA", "stat": 7, "player_link": "https://www.nba.com/stats/player/1630163/", "photo": "https://cdn.nba.com/headshots/nba/latest/1040x760/1630163.png", "ppg": "20.0", "rpg": "5.0", "apg": "7.9", "pie": "--", "team_logo": "https://cdn.nba.com/logos/nba/1610612766/primary/D/logo.svg"},
{"category": "Turnovers", "place": 2, "player_name": "Donovan Mitchell", "team_name": "CLE", "stat": 4, "player_link": "https://www.nba.com/stats/player/1628378/", "photo": "https://cdn.nba.com/headshots/nba/latest/1040x760/1628378.png", "ppg": "29.8", "rpg": "4.8", "apg": "5.5", "pie": "--", "team_logo": "https://cdn.nba.com/logos/nba/1610612739/primary/L/logo.svg"},
{"category": "Turnovers", "place": 2, "player_name": "T.J. McConnell", "team_name": "IND", "stat": 4, "player_link": "https://www.nba.com/stats/player/204456/", "photo": "https://cdn.nba.com/headshots/nba/latest/1040x760/204456.png", "ppg": "10.2", "rpg": "2.5", "apg": "4.8", "pie": "--", "team_logo": "https://cdn.nba.com/logos/nba/1610612754/primary/D/logo.svg"},
{"category": "Turnovers", "place": 2, "player_name": "Anthony Edwards", "team_name": "MIN", "stat": 4, "player_link": "https://www.nba.com/stats/player/1630162/", "photo": "https://cdn.nba.com/headshots/nba/latest/1040x760/1630162.png", "ppg": "29.2", "rpg": "5.1", "apg": "3.8", "pie": "--", "team_logo": "https://cdn.nba.com/logos/nba/1610612750/primary/D/logo.svg"},
{"category": "Turnovers", "place": 2, "player_name": "Isaiah Collier", "team_name": "UTA", "stat": 4, "player_link": "https://www.nba.com/stats/player/1642268/", "photo": "https://cdn.nba.com/headshots/nba/latest/1040x760/1642268.png", "ppg": "8.3", "rpg": "2.3", "apg": "6.6", "pie": "--", "team_logo": "https://cdn.nba.com/logos/nba/1610612762/primary/D/logo.svg"},
{"category": "Turnovers", "place": 1, "player_name": "Pascal Siakam", "team_name": "IND", "stat": 6, "player_link": "https://www.nba.com/stats/player/1627783/", "photo": "https://cdn.nba.com/headshots/nba/latest/1040x760/1627783.png", "ppg": "23.9", "rpg": "6.8", "apg": "3.8", "pie": "--", "team_logo": "https://cdn.nba.com/logos/nba/1610612754/primary/D/logo.svg"},
{"category": "Steals", "place": 5, "player_name": "Jarrett Allen", "team_name": "CLE", "stat": 2, "player_link": "https://www.nba.com/stats/player/1628386/", "photo": "https://cdn.nba.com/headshots/nba/latest/1040x760/1628386.png", "ppg": "13.8", "rpg": "8.0", "apg": "2.1", "pie": "--", "team_logo": "https://cdn.nba.com/logos/nba/1610612739/primary/L/logo.svg"},
{"category": "Steals", "place": 2, "player_name": "Keyonte George", "team_name": "UTA", "stat": 3, "player_link": "https://www.nba.com/stats/player/1641718/", "photo": "https://cdn.nba.com/headshots/nba/latest/1040x760/1641718.png", "ppg": "24.1", "rpg": "4.3", "apg": "6.9", "pie": "--", "team_logo": "https://cdn.nba.com/logos/nba/1610612762/primary/D/logo.svg"},
{"category": "Steals", "place": 2, "player_name": "Cooper Flagg", "team_name": "DAL", "stat": 3, "player_link": "https://www.nba.com/stats/player/1642843/", "photo": "https://cdn.nba.com/headshots/nba/latest/1040x760/1642843.png", "ppg": "19.1", "rpg": "6.6", "apg": "4.3", "pie": "--", "team_logo": "https://cdn.nba.com/logos/nba/1610612742/primary/D/logo.svg"},
{"category": "Steals", "place": 2, "player_name": "LaMelo Ball", "team_name": "CHA", "stat": 3, "player_link": "https://www.nba.com/stats/player/1630163/", "photo": "https://cdn.nba.com/headshots/nba/latest/1040x760/1630163.png", "ppg": "20.0", "rpg": "5.0", "apg": "7.9", "pie": "--", "team_logo": "https://cdn.nba.com/logos/nba/1610612766/primary/D/logo.svg"},
{"category": "Steals", "place": 1, "player_name": "T.J. McConnell", "team_name": "IND", "stat": 4, "player_link": "https://www.nba.com/stats/player/204456/", "photo": "https://cdn.nba.com/headshots/nba/latest/1040x760/204456.png", "ppg": "10.2", "rpg": "2.5", "apg": "4.8", "pie": "--", "team_logo": "https://cdn.nba.com/logos/nba/1610612754/primary/D/logo.svg"},
{"category": "Blocks", "place": 4, "player_name": "Anthony Davis", "team_name": "DAL", "stat": 1, "player_link": "https://www.nba.com/stats/player/203076/", "photo": "https://cdn.nba.com/headshots/nba/latest/1040x760/203076.png", "ppg": "20.4", "rpg": "11.1", "apg": "2.8", "pie": "--", "team_logo": "https://cdn.nba.com/logos/nba/1610612742/primary/D/logo.svg"},
{"category": "Blocks", "place": 4, "player_name": "Isaiah Collier", "team_name": "UTA", "stat": 1, "player_link": "https://www.nba.com/stats/player/1642268/", "photo": "https://cdn.nba.com/headshots/nba/latest/1040x760/1642268.png", "ppg": "8.3", "rpg": "2.3", "apg": "6.6", "pie": "--", "team_logo": "https://cdn.nba.com/logos/nba/1610612762/primary/D/logo.svg"},
{"category": "Blocks", "place": 2, "player_name": "Brandon Miller", "team_name": "CHA", "stat": 2, "player_link": "https://www.nba.com/stats/player/1641706/", "photo": "https://cdn.nba.com/headshots/nba/latest/1040x760/1641706.png", "ppg": "19.4", "rpg": "4.2", "apg": "3.3", "pie": "--", "team_logo": "https://cdn.nba.com/logos/nba/1610612766/primary/D/logo.svg"},
{"category": "Blocks", "place": 2, "player_name": "Lauri Markkanen", "team_name": "UTA", "stat": 2, "player_link": "https://www.nba.com/stats/player/1628374/", "photo": "https://cdn.nba.com/headshots/nba/latest/1040x760/1628374.png", "ppg": "27.9", "rpg": "7.0", "apg": "2.2", "pie": "--", "team_logo": "https://cdn.nba.com/logos/nba/1610612762/primary/D/logo.svg"},
{"category": "Blocks", "place": 1, "player_name": "Jay Huff", "team_name": "IND", "stat": 3, "player_link": "https://www.nba.com/stats/player/1630643/", "photo": "https://cdn.nba.com/headshots/nba/latest/1040x760/1630643.png", "ppg": "8.1", "rpg": "3.8", "apg": "1.3", "pie": "--", "team_logo": "https://cdn.nba.com/logos/nba/1610612754/primary/D/logo.svg"},
{"category": "Assists", "place": 2, "player_name": "T.J. McConnell", "team_name": "IND", "stat": 8, "player_link": "https://www.nba.com/stats/player/204456/", "photo": "https://cdn.nba.com/headshots/nba/latest/1040x760/204456.png", "ppg": "10.2", "rpg": "2.5", "apg": "4.8", "pie": "--", "team_logo": "https://cdn.nba.com/logos/nba/1610612754/primary/D/logo.svg"},
{"category": "Assists", "place": 2, "player_name": "Darius Garland", "team_name": "CLE", "stat": 8, "player_link": "https://www.nba.com/stats/player/1629636/", "photo": "https://cdn.nba.com/headshots/nba/latest/1040x760/1629636.png", "ppg": "17.5", "rpg": "2.5", "apg": "6.9", "pie": "--", "team_logo": "https://cdn.nba.com/logos/nba/1610612739/primary/L/logo.svg"},
{"category": "Assists", "place": 2, "player_name": "Cooper Flagg", "team_name": "DAL", "stat": 8, "player_link": "https://www.nba.com/stats/player/1642843/", "photo": "https://cdn.nba.com/headshots/nba/latest/1040x760/1642843.png", "ppg": "19.1", "rpg": "6.6", "apg": "4.3", "pie": "--", "team_logo": "https://cdn.nba.com/logos/nba/1610612742/primary/D/logo.svg"},
{"category": "Assists", "place": 2, "player_name": "LaMelo Ball", "team_name": "CHA", "stat": 8, "player_link": "https://www.nba.com/stats/player/1630163/", "photo": "https://cdn.nba.com/headshots/nba/latest/1040x760/1630163.png", "ppg": "20.0", "rpg": "5.0", "apg": "7.9", "pie": "--", "team_logo": "https://cdn.nba.com/logos/nba/1610612766/primary/D/logo.svg"}
]