[
{"category": "Assists", "place": 1, "player_name": "Julius Randle", "team_name": "MIN", "stat": 14, "player_link": "https://www.nba.com/stats/player/203944/", "photo": "https://cdn.nba.com/headshots/nba/latest/1040x760/203944.png", "ppg": "22.4", "rpg": "7.0", "apg": "5.9", "pie": "--", "team_logo": "https://cdn.nba.com/logos/nba/1610612750/primary/D/logo.svg"},
{"category": "Rebounds", "place": 4, "player_name": "Karl-Anthony Towns", "team_name": "NYK", "stat": 12, "player_link": "https://www.nba.com/stats/player/1626157/", "photo": "https://cdn.nba.com/headshots/nba/latest/1040x760/1626157.png", "ppg": "22.0", "rpg": "11.9", "apg": "2.9", "pie": "--", "team_logo": "https://cdn.nba.com/logos/nba/1610612752/primary/L/logo.svg"},
{"category": "Rebounds", "place": 4, "player_name": "Collin Murray-Boyles", "team_name": "TOR", "stat": 12, "player_link": "https://www.nba.com/stats/player/1642867/", "photo": "https://cdn.nba.com/headshots/nba/latest/1040x760/1642867.png", "ppg": "6.9", "rpg": "4.1", "apg": "1.4", "pie": "--", "team_logo": "https://cdn.nba.com/logos/nba/1610612761/primary/D/logo.svg"},
{"category": "Rebounds", "place": 2, "player_name": "Victor Wembanyama", "team_name": "SAS", "stat": 14, "player_link": "https://www.nba.com/stats/player/1641705/", "photo": "https://cdn.nba.com/headshots/nba/latest/1040x760/1641705.png", "ppg": "24.0", "rpg": "11.7", "apg": "3.5", "pie": "--", "team_logo": "https://cdn.nba.com/logos/nba/1610612759/primary/D/logo.svg"},
{"category": "Rebounds", "place": 1, "player_name": "Paolo Banchero", "team_name": "ORL", "stat": 15, "player_link": "https://www.nba.com/stats/player/1631094/", "photo": "https://cdn.nba.com/headshots/nba/latest/1040x760/1631094.png", "ppg": "19.9", "rpg": "8.5", "apg": "4.7", "pie": "--", "team_logo": "https://cdn.nba.com/logos/nba/1610612753/primary/L/logo.svg"},
{"category": "Rebounds", "place": 2, "player_name": "Onyeka Okongwu", "team_name": "ATL", "stat": 14, "player_link": "https://www.nba.com/stats/player/1630168/", "photo": "https://cdn.nba.com/headshots/nba/latest/1040x760/1630168.png", "ppg": "16.4", "rpg": "7.8", "apg": "3.2", "pie": "--", "team_logo": "https://cdn.nba.com/logos/nba/1610612737/primary/L/logo.svg"},
{"category": "Points", "place": 5, "player_name": "Nickeil Alexander-Walker", "team_name": "ATL", "stat": 30, "player_link": "https://www.nba.com/stats/player/1629638/", "photo": "https://cdn.nba.com/headshots/nba/latest/1040x760/1629638.png", "ppg": "20.6", "rpg": "3.4", "apg": "3.3", "pie": "--", "team_logo": "https://cdn.nba.com/logos/nba/1610612737/primary/L/logo.svg"},
{"category": "Points", "place": 4, "player_name": "Brandon Miller", "team_name": "CHA", "stat": 31, "player_link": "https://www.nba.com/stats/player/1641706/", "photo": "https://cdn.nba.com/headshots/nba/latest/1040x760/1641706.png", "ppg": "18.8", "rpg": "4.0", "apg": "3.4", "pie": "--", "team_logo": "https://cdn.nba.com/logos/nba/1610612766/primary/D/logo.svg"},
{"category": "Points", "place": 3, "player_name": "Zion Williamson", "team_name": "NOP", "stat": 32, "player_link": "https://www.nba.com/stats/player/1629627/", "photo": "https://cdn.nba.com/headshots/nba/latest/1040x760/1629627.png", "ppg": "22.3", "rpg": "5.7", "apg": "3.4", "pie": "--", "team_logo": "https://cdn.nba.com/logos/nba/1610612740/primary/D/logo.svg"},
{"category": "Points", "place": 2, "player_name": "Naz Reid", "team_name": "MIN", "stat": 33, "player_link": "https://www.nba.com/stats/player/1629675/", "photo": "https://cdn.nba.com/headshots/nba/latest/1040x760/1629675.png", "ppg": "14.3", "rpg": "6.2", "apg": "2.4", "pie": "--", "team_logo": "https://cdn.nba.com/logos/nba/1610612750/primary/D/logo.svg"},
{"category": "Points", "place": 1, "player_name": "Shai Gilgeous-Alexander", "team_name": "OKC", "stat": 39, "player_link": "https://www.nba.com/stats/player/1628983/", "photo": "https://cdn.nba.com/headshots/nba/latest/1040x760/1628983.png", "ppg": "32.2", "rpg": "4.8", "apg": "6.4", "pie": "--", "team_logo": "https://cdn.nba.com/logos/nba/1610612760/primary/L/logo.svg"},
{"category": "Three Pointers Made", "place": 2, "player_name": "Naz Reid", "team_name": "MIN", "stat": 6, "player_link": "https://www.nba.com/stats/player/1629675/", "photo": "https://cdn.nba.com/headshots/nba/latest/1040x760/1629675.png", "ppg": "14.3", "rpg": "6.2", "apg": "2.4", "pie": "--", "team_logo": "https://cdn.nba.com/logos/nba/1610612750/primary/D/logo.svg"},
{"category": "Three Pointers Made", "place": 2, "player_name": "Caleb Love", "team_name": "POR", "stat": 6, "player_link": "https://www.nba.com/stats/player/1631126/", "photo": "https://cdn.nba.com/headshots/nba/latest/1040x760/1631126.png", "ppg": "9.2", "rpg": "2.3", "apg": "2.1", "pie": "--", "team_logo": "https://cdn.nba.com/logos/nba/1610612757/primary/L/logo.svg"},
{"category": "Three Pointers Made", "place": 2, "player_name": "LaMelo Ball", "team_name": "CHA", "stat": 6, "player_link": "https://www.nba.com/stats/player/1630163/", "photo": "https://cdn.nba.com/headshots/nba/latest/1040x760/1630163.png", "ppg": "20.0", "rpg": "5.3", "apg": "8.4", "pie": "--", "team_logo": "https://cdn.nba.com/logos/nba/1610612766/primary/D/logo.svg"},
{"category": "Three Pointers Made", "place": 2, "player_name": "Nickeil Alexander-Walker", "team_name": "ATL", "stat": 6, "player_link": "https://www.nba.com/stats/player/1629638/", "photo": "https://cdn.nba.com/headshots/nba/latest/1040x760/1629638.png", "ppg": "20.6", "rpg": "3.4", "apg": "3.3", "pie": "--", "team_logo": "https://cdn.nba.com/logos/nba/1610612737/primary/L/logo.svg"},
{"category": "Three Pointers Made", "place": 1, "player_name": "Egor Dëmin", "team_name": "BKN", "stat": 7, "player_link": "https://www.nba.com/stats/player/1642856/", "photo": "https://cdn.nba.com/headshots/nba/latest/1040x760/1642856.png", "ppg": "9.8", "rpg": "3.1", "apg": "3.4", "pie": "--", "team_logo": "https://cdn.nba.com/logos/nba/1610612751/primary/D/logo.svg"},
{"category": "Fantasy Points", "place": 5, "player_name": "Michael Porter Jr.", "team_name": "BKN", "stat": 52.3, "player_link": "https://www.nba.com/stats/player/1629008/", "photo": "https://cdn.nba.com/headshots/nba/latest/1040x760/1629008.png", "ppg": "25.8", "rpg": "7.5", "apg": "3.3", "pie": "--", "team_logo": "https://cdn.nba.com/logos/nba/1610612751/primary/D/logo.svg"},
{"category": "Fantasy Points", "place": 4, "player_name": "Brandon Miller", "team_name": "CHA", "stat": 53.1, "player_link": "https://www.nba.com/stats/player/1641706/", "photo": "https://cdn.nba.com/headshots/nba/latest/1040x760/1641706.png", "ppg": "18.8", "rpg": "4.0", "apg": "3.4", "pie": "--", "team_logo": "https://cdn.nba.com/logos/nba/1610612766/primary/D/logo.svg"},
{"category": "Fantasy Points", "place": 3, "player_name": "Deni Avdija", "team_name": "POR", "stat": 54.3, "player_link": "https://www.nba.com/stats/player/1630166/", "photo": "https://cdn.nba.com/headshots/nba/latest/1040x760/1630166.png", "ppg": "25.6", "rpg": "7.2", "apg": "6.9", "pie": "--", "team_logo": "https://cdn.nba.com/logos/nba/1610612757/primary/L/logo.svg"},
{"category": "Fantasy Points", "place": 2, "player_name": "Paolo Banchero", "team_name": "ORL", "stat": 58.0, "player_link": "https://www.nba.com/stats/player/1631094/", "photo": "https://cdn.nba.com/headshots/nba/latest/1040x760/1631094.png", "ppg": "19.9", "rpg": "8.5", "apg": "4.7", "pie": "--", "team_logo": "https://cdn.nba.com/logos/nba/1610612753/primary/L/logo.svg"},
{"category": "Fantasy Points", "place": 1, "player_name": "Shai Gilgeous-Alexander", "team_name": "OKC", "stat": 58.2, "player_link": "https://www.nba.com/stats/player/1628983/", "photo": "https://cdn.nba.com/headshots/nba/latest/1040x760/1628983.png", "ppg": "32.2", "rpg": "4.8", "apg": "6.4", "pie": "--", "team_logo": "https://cdn.nba.com/logos/nba/1610612760/primary/L/logo.svg"},
{"category": "Free Throws Made", "place": 5, "player_name": "Deni Avdija", "team_name": "POR", "stat": 8, "player_link": "https://www.nba.com/stats/player/1630166/", "photo": "https://cdn.nba.com/headshots/nba/latest/1040x760/1630166.png", "ppg": "25.6", "rpg": "7.2", "apg": "6.9", "pie": "--", "team_logo": "https://cdn.nba.com/logos/nba/1610612757/primary/L/logo.svg"},
{"category": "Free Throws Made", "place": 2, "player_name": "Zion Williamson", "team_name": "NOP", "stat": 10, "player_link": "https://www.nba.com/stats/player/1629627/", "photo": "https://cdn.nba.com/headshots/nba/latest/1040x760/1629627.png", "ppg": "22.3", "rpg": "5.7", "apg": "3.4", "pie": "--", "team_logo": "https://cdn.nba.com/logos/nba/1610612740/primary/D/logo.svg"},
{"category": "Free Throws Made", "place": 2, "player_name": "Victor Wembanyama", "team_name": "SAS", "stat": 10, "player_link": "https://www.nba.com/stats/player/1641705/", "photo": "https://cdn.nba.com/headshots/nba/latest/1040x760/1641705.png", "ppg": "24.0", "rpg": "11.7", "apg": "3.5", "pie": "--", "team_logo": "https://cdn.nba.com/logos/nba/1610612759/primary/D/logo.svg"},
{"category": "Free Throws Made", "place": 2, "player_name": "Brandon Miller", "team_name": "CHA", "stat": 10, "player_link": "https://www.nba.com/stats/player/1641706/", "photo": "https://cdn.nba.com/headshots/nba/latest/1040x760/1641706.png", "ppg": "18.8", "rpg": "4.0", "apg": "3.4", "pie": "--", "team_logo": "https://cdn.nba.com/logos/nba/1610612766/primary/D/logo.svg"},
{"category": "Free Throws Made", "place": 1, "player_name": "Jimmy Butler III", "team_name": "GSW", "stat": 11, "player_link": "https://www.nba.com/stats/player/202710/", "photo": "https://cdn.nba.com/headshots/nba/latest/1040x760/202710.png", "ppg": "19.7", "rpg": "5.6", "apg": "4.9", "pie": "--", "team_logo": "https://cdn.nba.com/logos/nba/1610612744/primary/D/logo.svg"},
{"category": "Turnovers", "place": 5, "player_name": "Anthony Black", "team_name": "ORL", "stat": 4, "player_link": "https://www.nba.com/stats/player/1641710/", "photo": "https://cdn.nba.com/headshots/nba/latest/1040x760/1641710.png", "ppg": "15.5", "rpg": "4.2", "apg": "3.5", "pie": "--", "team_logo": "https://cdn.nba.com/logos/nba/1610612753/primary/L/logo.svg"},
{"category": "Turnovers", "place": 3, "player_name": "Cooper Flagg", "team_name": "DAL", "stat": 5, "player_link": "https://www.nba.com/stats/player/1642843/", "photo": "https://cdn.nba.com/headshots/nba/latest/1040x760/1642843.png", "ppg": "19.4", "rpg": "6.4", "apg": "4.0", "pie": "--", "team_logo": "https://cdn.nba.com/logos/nba/1610612742/primary/D/logo.svg"},
{"category": "Turnovers", "place": 3, "player_name": "Stephon Castle", "team_name": "SAS", "stat": 5, "player_link": "https://www.nba.com/stats/player/1642264/", "photo": "https://cdn.nba.com/headshots/nba/latest/1040x760/1642264.png", "ppg": "18.5", "rpg": "5.0", "apg": "7.0", "pie": "--", "team_logo": "https://cdn.nba.com/logos/nba/1610612759/primary/D/logo.svg"},
{"category": "Turnovers", "place": 1, "player_name": "LaMelo Ball", "team_name": "CHA", "stat": 6, "player_link": "https://www.nba.com/stats/player/1630163/", "photo": "https://cdn.nba.com/headshots/nba/latest/1040x760/1630163.png", "ppg": "20.0", "rpg": "5.3", "apg": "8.4", "pie": "--", "team_logo": "https://cdn.nba.com/logos/nba/1610612766/primary/D/logo.svg"},
{"category": "Turnovers", "place": 1, "player_name": "Deni Avdija", "team_name": "POR", "stat": 6, "player_link": "https://www.nba.com/stats/player/1630166/", "photo": "https://cdn.nba.com/headshots/nba/latest/1040x760/1630166.png", "ppg": "25.6", "rpg": "7.2", "apg": "6.9", "pie": "--", "team_logo": "https://cdn.nba.com/logos/nba/1610612757/primary/L/logo.svg"},
{"category": "Steals", "place": 1, "player_name": "Spencer Jones", "team_name": "DEN", "stat": 3, "player_link": "https://www.nba.com/stats/player/1642461/", "photo": "https://cdn.nba.com/headshots/nba/latest/1040x760/1642461.png", "ppg": "6.0", "rpg": "2.6", "apg": "1.0", "pie": "--", "team_logo": "https://cdn.nba.com/logos/nba/1610612743/primary/D/logo.svg"},
{"category": "Steals", "place": 1, "player_name": "Cooper Flagg", "team_name": "DAL", "stat": 3, "player_link": "https://www.nba.com/stats/player/1642843/", "photo": "https://cdn.nba.com/headshots/nba/latest/1040x760/1642843.png", "ppg": "19.4", "rpg": "6.4", "apg": "4.0", "pie": "--", "team_logo": "https://cdn.nba.com/logos/nba/1610612742/primary/D/logo.svg"},
{"category": "Steals", "place": 1, "player_name": "Nic Claxton", "team_name": "BKN", "stat": 3, "player_link": "https://www.nba.com/stats/player/1629651/", "photo": "https://cdn.nba.com/headshots/nba/latest/1040x760/1629651.png", "ppg": "13.6", "rpg": "7.8", "apg": "4.3", "pie": "--", "team_logo": "https://cdn.nba.com/logos/nba/1610612751/primary/D/logo.svg"},
{"category": "Steals", "place": 1, "player_name": "Jaylen Clark", "team_name": "MIN", "stat": 3, "player_link": "https://www.nba.com/stats/player/1641740/", "photo": "https://cdn.nba.com/headshots/nba/latest/1040x760/1641740.png", "ppg": "4.5", "rpg": "2.0", "apg": "0.5", "pie": "--", "team_logo": "https://cdn.nba.com/logos/nba/1610612750/primary/D/logo.svg"},
{"category": "Steals", "place": 1, "player_name": "OG Anunoby", "team_name": "NYK", "stat": 3, "player_link": "https://www.nba.com/stats/player/1628384/", "photo": "https://cdn.nba.com/headshots/nba/latest/1040x760/1628384.png", "ppg": "15.5", "rpg": "5.5", "apg": "2.0", "pie": "--", "team_logo": "https://cdn.nba.com/logos/nba/1610612752/primary/L/logo.svg"},
{"category": "Blocks", "place": 3, "player_name": "Daniel Gafford", "team_name": "DAL", "stat": 3, "player_link": "https://www.nba.com/stats/player/1629655/", "photo": "https://cdn.nba.com/headshots/nba/latest/1040x760/1629655.png", "ppg": "8.2", "rpg": "6.0", "apg": "1.0", "pie": "--", "team_logo": "https://cdn.nba.com/logos/nba/1610612742/primary/D/logo.svg"},
{"category": "Blocks", "place": 3, "player_name": "Nic Claxton", "team_name": "BKN", "stat": 3, "player_link": "https://www.nba.com/stats/player/1629651/", "photo": "https://cdn.nba.com/headshots/nba/latest/1040x760/1629651.png", "ppg": "13.6", "rpg": "7.8", "apg": "4.3", "pie": "--", "team_logo": "https://cdn.nba.com/logos/nba/1610612751/primary/D/logo.svg"},
{"category": "Blocks", "place": 3, "player_name": "Marvin Bagley III", "team_name": "WAS", "stat": 3, "player_link": "https://www.nba.com/stats/player/1628963/", "photo": "https://cdn.nba.com/headshots/nba/latest/1040x760/1628963.png", "ppg": "10.1", "rpg": "5.6", "apg": "1.6", "pie": "--", "team_logo": "https://cdn.nba.com/logos/nba/1610612764/primary/D/logo.svg"},
{"category": "Blocks", "place": 1, "player_name": "Myles Turner", "team_name": "MIL", "stat": 4, "player_link": "https://www.nba.com/stats/player/1626167/", "photo": "https://cdn.nba.com/headshots/nba/latest/1040x760/1626167.png", "ppg": "12.6", "rpg": "5.4", "apg": "1.6", "pie": "--", "team_logo": "https://cdn.nba.com/logos/nba/1610612749/primary/D/logo.svg"},
{"category": "Blocks", "place": 1, "player_name": "Rudy Gobert", "team_name": "MIN", "stat": 4, "player_link": "https://www.nba.com/stats/player/203497/", "photo": "https://cdn.nba.com/headshots/nba/latest/1040x760/203497.png", "ppg": "11.2", "rpg": "11.0", "apg": "1.8", "pie": "--", "team_logo": "https://cdn.nba.com/logos/nba/1610612750/primary/D/logo.svg"},
{"category": "Assists", "place": 2, "player_name": "Jamal Murray", "team_name": "DEN", "stat": 11, "player_link": "https://www.nba.com/stats/player/1627750/", "photo": "https://cdn.nba.com/headshots/nba/latest/1040x760/1627750.png", "ppg": "25.2", "rpg": "4.4", "apg": "7.0", "pie": "--", "team_logo": "https://cdn.nba.com/logos/nba/1610612743/primary/D/logo.svg"},
{"category": "Assists", "place": 2, "player_name": "Deni Avdija", "team_name": "POR", "stat": 11, "player_link": "https://www.nba.com/stats/player/1630166/", "photo": "https://cdn.nba.com/headshots/nba/latest/1040x760/1630166.png", "ppg": "25.6", "rpg": "7.2", "apg": "6.9", "pie": "--", "team_logo": "https://cdn.nba.com/logos/nba/1610612757/primary/L/logo.svg"},
{"category": "Assists", "place": 2, "player_name": "Jaime Jaquez Jr.", "team_name": "MIA", "stat": 11, "player_link": "https://www.nba.com/stats/player/1631170/", "photo": "https://cdn.nba.com/headshots/nba/latest/1040x760/1631170.png", "ppg": "16.4", "rpg": "5.4", "apg": "4.8", "pie": "--", "team_logo": "https://cdn.nba.com/logos/nba/1610612748/primary/L/logo.svg"},
{"category": "Assists", "place": 2, "player_name": "Darius Garland", "team_name": "CLE", "stat": 11, "player_link": "https://www.nba.com/stats/player/1629636/", "photo": "https://cdn.nba.com/headshots/nba/latest/1040x760/1629636.png", "ppg": "16.9", "rpg": "2.8", "apg": "6.9", "pie": "--", "team_logo": "https://cdn.nba.com/logos/nba/1610612739/primary/L/logo.svg"}
]