[
{"category": "Points", "place": 3, "player_name": "Ivica Zubac", "team_name": "LAC", "stat": 28, "player_link": "https://www.nba.com/stats/player/1627826/", "photo": "https://cdn.nba.com/headshots/nba/latest/1040x760/1627826.png", "ppg": "16.4", "rpg": "12.6", "apg": "2.6", "pie": "--", "team_logo": "https://cdn.nba.com/logos/nba/1610612746/primary/D/logo.svg"},
{"category": "Points", "place": 2, "player_name": "Trae Young", "team_name": "ATL", "stat": 31, "player_link": "https://www.nba.com/stats/player/1629027/", "photo": "https://cdn.nba.com/headshots/nba/latest/1040x760/1629027.png", "ppg": "24.1", "rpg": "3.2", "apg": "11.4", "pie": "--", "team_logo": "https://cdn.nba.com/logos/nba/1610612737/primary/L/logo.svg"},
{"category": "Points", "place": 1, "player_name": "Kawhi Leonard", "team_name": "LAC", "stat": 33, "player_link": "https://www.nba.com/stats/player/202695/", "photo": "https://cdn.nba.com/headshots/nba/latest/1040x760/202695.png", "ppg": "19.6", "rpg": "5.3", "apg": "2.9", "pie": "--", "team_logo": "https://cdn.nba.com/logos/nba/1610612746/primary/D/logo.svg"},
{"category": "Turnovers", "place": 2, "player_name": "Derrick White", "team_name": "BOS", "stat": 4, "player_link": "https://www.nba.com/stats/player/1628401/", "photo": "https://cdn.nba.com/headshots/nba/latest/1040x760/1628401.png", "ppg": "16.7", "rpg": "4.4", "apg": "4.4", "pie": "--", "team_logo": "https://cdn.nba.com/logos/nba/1610612738/primary/D/logo.svg"},
{"category": "Turnovers", "place": 1, "player_name": "Jimmy Butler III", "team_name": "GSW", "stat": 5, "player_link": "https://www.nba.com/stats/player/202710/", "photo": "https://cdn.nba.com/headshots/nba/latest/1040x760/202710.png", "ppg": "17.1", "rpg": "5.5", "apg": "5.3", "pie": "--", "team_logo": "https://cdn.nba.com/logos/nba/1610612744/primary/D/logo.svg"},
{"category": "Turnovers", "place": 2, "player_name": "Kristaps Porziņģis", "team_name": "BOS", "stat": 4, "player_link": "https://www.nba.com/stats/player/204001/", "photo": "https://cdn.nba.com/headshots/nba/latest/1040x760/204001.png", "ppg": "19.3", "rpg": "6.8", "apg": "1.9", "pie": "--", "team_logo": "https://cdn.nba.com/logos/nba/1610612738/primary/D/logo.svg"},
{"category": "Steals", "place": 2, "player_name": "Jrue Holiday", "team_name": "BOS", "stat": 3, "player_link": "https://www.nba.com/stats/player/201950/", "photo": "https://cdn.nba.com/headshots/nba/latest/1040x760/201950.png", "ppg": "11.0", "rpg": "4.3", "apg": "3.8", "pie": "--", "team_logo": "https://cdn.nba.com/logos/nba/1610612738/primary/D/logo.svg"},
{"category": "Steals", "place": 2, "player_name": "Marcus Garrett", "team_name": "CHA", "stat": 3, "player_link": "https://www.nba.com/stats/player/1630585/", "photo": "https://cdn.nba.com/headshots/nba/latest/1040x760/1630585.png", "ppg": "7.0", "rpg": "1.5", "apg": "3.3", "pie": "--", "team_logo": "https://cdn.nba.com/logos/nba/1610612766/primary/D/logo.svg"},
{"category": "Steals", "place": 2, "player_name": "Dyson Daniels", "team_name": "ATL", "stat": 3, "player_link": "https://www.nba.com/stats/player/1630700/", "photo": "https://cdn.nba.com/headshots/nba/latest/1040x760/1630700.png", "ppg": "14.1", "rpg": "5.6", "apg": "4.3", "pie": "--", "team_logo": "https://cdn.nba.com/logos/nba/1610612737/primary/L/logo.svg"},
{"category": "Steals", "place": 2, "player_name": "Giannis Antetokounmpo", "team_name": "MIL", "stat": 3, "player_link": "https://www.nba.com/stats/player/203507/", "photo": "https://cdn.nba.com/headshots/nba/latest/1040x760/203507.png", "ppg": "30.2", "rpg": "12.0", "apg": "6.0", "pie": "--", "team_logo": "https://cdn.nba.com/logos/nba/1610612749/primary/D/logo.svg"},
{"category": "Steals", "place": 1, "player_name": "Kawhi Leonard", "team_name": "LAC", "stat": 4, "player_link": "https://www.nba.com/stats/player/202695/", "photo": "https://cdn.nba.com/headshots/nba/latest/1040x760/202695.png", "ppg": "19.6", "rpg": "5.3", "apg": "2.9", "pie": "--", "team_logo": "https://cdn.nba.com/logos/nba/1610612746/primary/D/logo.svg"},
{"category": "Blocks", "place": 3, "player_name": "Moussa Diabaté", "team_name": "CHA", "stat": 2, "player_link": "https://www.nba.com/stats/player/1631217/", "photo": "https://cdn.nba.com/headshots/nba/latest/1040x760/1631217.png", "ppg": "5.2", "rpg": "6.4", "apg": "0.9", "pie": "--", "team_logo": "https://cdn.nba.com/logos/nba/1610612766/primary/D/logo.svg"},
{"category": "Blocks", "place": 3, "player_name": "Dominick Barlow", "team_name": "ATL", "stat": 2, "player_link": "https://www.nba.com/stats/player/1631230/", "photo": "https://cdn.nba.com/headshots/nba/latest/1040x760/1631230.png", "ppg": "3.9", "rpg": "1.9", "apg": "0.4", "pie": "--", "team_logo": "https://cdn.nba.com/logos/nba/1610612737/primary/L/logo.svg"},
{"category": "Blocks", "place": 3, "player_name": "Giannis Antetokounmpo", "team_name": "MIL", "stat": 2, "player_link": "https://www.nba.com/stats/player/203507/", "photo": "https://cdn.nba.com/headshots/nba/latest/1040x760/203507.png", "ppg": "30.2", "rpg": "12.0", "apg": "6.0", "pie": "--", "team_logo": "https://cdn.nba.com/logos/nba/1610612749/primary/D/logo.svg"},
{"category": "Blocks", "place": 2, "player_name": "Kristaps Porziņģis", "team_name": "BOS", "stat": 3, "player_link": "https://www.nba.com/stats/player/204001/", "photo": "https://cdn.nba.com/headshots/nba/latest/1040x760/204001.png", "ppg": "19.3", "rpg": "6.8", "apg": "1.9", "pie": "--", "team_logo": "https://cdn.nba.com/logos/nba/1610612738/primary/D/logo.svg"},
{"category": "Blocks", "place": 1, "player_name": "Draymond Green", "team_name": "GSW", "stat": 4, "player_link": "https://www.nba.com/stats/player/203110/", "photo": "https://cdn.nba.com/headshots/nba/latest/1040x760/203110.png", "ppg": "9.1", "rpg": "6.1", "apg": "5.7", "pie": "--", "team_logo": "https://cdn.nba.com/logos/nba/1610612744/primary/D/logo.svg"},
{"category": "Fantasy Points", "place": 5, "player_name": "Trae Young", "team_name": "ATL", "stat": 50.4, "player_link": "https://www.nba.com/stats/player/1629027/", "photo": "https://cdn.nba.com/headshots/nba/latest/1040x760/1629027.png", "ppg": "24.1", "rpg": "3.2", "apg": "11.4", "pie": "--", "team_logo": "https://cdn.nba.com/logos/nba/1610612737/primary/L/logo.svg"},
{"category": "Fantasy Points", "place": 4, "player_name": "Kristaps Porziņģis", "team_name": "BOS", "stat": 53.1, "player_link": "https://www.nba.com/stats/player/204001/", "photo": "https://cdn.nba.com/headshots/nba/latest/1040x760/204001.png", "ppg": "19.3", "rpg": "6.8", "apg": "1.9", "pie": "--", "team_logo": "https://cdn.nba.com/logos/nba/1610612738/primary/D/logo.svg"},
{"category": "Fantasy Points", "place": 3, "player_name": "Giannis Antetokounmpo", "team_name": "MIL", "stat": 55.3, "player_link": "https://www.nba.com/stats/player/203507/", "photo": "https://cdn.nba.com/headshots/nba/latest/1040x760/203507.png", "ppg": "30.2", "rpg": "12.0", "apg": "6.0", "pie": "--", "team_logo": "https://cdn.nba.com/logos/nba/1610612749/primary/D/logo.svg"},
{"category": "Fantasy Points", "place": 2, "player_name": "Ivica Zubac", "team_name": "LAC", "stat": 55.5, "player_link": "https://www.nba.com/stats/player/1627826/", "photo": "https://cdn.nba.com/headshots/nba/latest/1040x760/1627826.png", "ppg": "16.4", "rpg": "12.6", "apg": "2.6", "pie": "--", "team_logo": "https://cdn.nba.com/logos/nba/1610612746/primary/D/logo.svg"},
{"category": "Fantasy Points", "place": 1, "player_name": "Kawhi Leonard", "team_name": "LAC", "stat": 57.4, "player_link": "https://www.nba.com/stats/player/202695/", "photo": "https://cdn.nba.com/headshots/nba/latest/1040x760/202695.png", "ppg": "19.6", "rpg": "5.3", "apg": "2.9", "pie": "--", "team_logo": "https://cdn.nba.com/logos/nba/1610612746/primary/D/logo.svg"},
{"category": "Free Throws Made", "place": 4, "player_name": "Donovan Mitchell", "team_name": "CLE", "stat": 6, "player_link": "https://www.nba.com/stats/player/1628378/", "photo": "https://cdn.nba.com/headshots/nba/latest/1040x760/1628378.png", "ppg": "24.1", "rpg": "4.4", "apg": "4.9", "pie": "--", "team_logo": "https://cdn.nba.com/logos/nba/1610612739/primary/L/logo.svg"},
{"category": "Free Throws Made", "place": 4, "player_name": "Jonathan Kuminga", "team_name": "GSW", "stat": 6, "player_link": "https://www.nba.com/stats/player/1630228/", "photo": "https://cdn.nba.com/headshots/nba/latest/1040x760/1630228.png", "ppg": "16.3", "rpg": "4.8", "apg": "2.3", "pie": "--", "team_logo": "https://cdn.nba.com/logos/nba/1610612744/primary/D/logo.svg"},
{"category": "Free Throws Made", "place": 2, "player_name": "James Harden", "team_name": "LAC", "stat": 10, "player_link": "https://www.nba.com/stats/player/201935/", "photo": "https://cdn.nba.com/headshots/nba/latest/1040x760/201935.png", "ppg": "22.5", "rpg": "5.9", "apg": "8.7", "pie": "--", "team_logo": "https://cdn.nba.com/logos/nba/1610612746/primary/D/logo.svg"},
{"category": "Free Throws Made", "place": 2, "player_name": "Giannis Antetokounmpo", "team_name": "MIL", "stat": 10, "player_link": "https://www.nba.com/stats/player/203507/", "photo": "https://cdn.nba.com/headshots/nba/latest/1040x760/203507.png", "ppg": "30.2", "rpg": "12.0", "apg": "6.0", "pie": "--", "team_logo": "https://cdn.nba.com/logos/nba/1610612749/primary/D/logo.svg"},
{"category": "Free Throws Made", "place": 1, "player_name": "Jimmy Butler III", "team_name": "GSW", "stat": 11, "player_link": "https://www.nba.com/stats/player/202710/", "photo": "https://cdn.nba.com/headshots/nba/latest/1040x760/202710.png", "ppg": "17.1", "rpg": "5.5", "apg": "5.3", "pie": "--", "team_logo": "https://cdn.nba.com/logos/nba/1610612744/primary/D/logo.svg"},
{"category": "Three Pointers Made", "place": 2, "player_name": "Max Strus", "team_name": "CLE", "stat": 5, "player_link": "https://www.nba.com/stats/player/1629622/", "photo": "https://cdn.nba.com/headshots/nba/latest/1040x760/1629622.png", "ppg": "9.4", "rpg": "4.4", "apg": "3.1", "pie": "--", "team_logo": "https://cdn.nba.com/logos/nba/1610612739/primary/L/logo.svg"},
{"category": "Three Pointers Made", "place": 2, "player_name": "Zaccharie Risacher", "team_name": "ATL", "stat": 5, "player_link": "https://www.nba.com/stats/player/1642258/", "photo": "https://cdn.nba.com/headshots/nba/latest/1040x760/1642258.png", "ppg": "11.9", "rpg": "3.7", "apg": "1.2", "pie": "--", "team_logo": "https://cdn.nba.com/logos/nba/1610612737/primary/L/logo.svg"},
{"category": "Three Pointers Made", "place": 2, "player_name": "Kawhi Leonard", "team_name": "LAC", "stat": 5, "player_link": "https://www.nba.com/stats/player/202695/", "photo": "https://cdn.nba.com/headshots/nba/latest/1040x760/202695.png", "ppg": "19.6", "rpg": "5.3", "apg": "2.9", "pie": "--", "team_logo": "https://cdn.nba.com/logos/nba/1610612746/primary/D/logo.svg"},
{"category": "Three Pointers Made", "place": 2, "player_name": "Kyle Kuzma", "team_name": "MIL", "stat": 5, "player_link": "https://www.nba.com/stats/player/1628398/", "photo": "https://cdn.nba.com/headshots/nba/latest/1040x760/1628398.png", "ppg": "14.6", "rpg": "6.0", "apg": "2.3", "pie": "--", "team_logo": "https://cdn.nba.com/logos/nba/1610612749/primary/D/logo.svg"},
{"category": "Three Pointers Made", "place": 1, "player_name": "Baylor Scheierman", "team_name": "BOS", "stat": 6, "player_link": "https://www.nba.com/stats/player/1631248/", "photo": "https://cdn.nba.com/headshots/nba/latest/1040x760/1631248.png", "ppg": "2.6", "rpg": "1.5", "apg": "0.7", "pie": "--", "team_logo": "https://cdn.nba.com/logos/nba/1610612738/primary/D/logo.svg"},
{"category": "Turnovers", "place": 5, "player_name": "Damion Baugh", "team_name": "CHA", "stat": 3, "player_link": "https://www.nba.com/stats/player/1641878/", "photo": "https://cdn.nba.com/headshots/nba/latest/1040x760/1641878.png", "ppg": "8.3", "rpg": "3.1", "apg": "3.9", "pie": "--", "team_logo": "https://cdn.nba.com/logos/nba/1610612766/primary/D/logo.svg"},
{"category": "Turnovers", "place": 2, "player_name": "Trae Young", "team_name": "ATL", "stat": 4, "player_link": "https://www.nba.com/stats/player/1629027/", "photo": "https://cdn.nba.com/headshots/nba/latest/1040x760/1629027.png", "ppg": "24.1", "rpg": "3.2", "apg": "11.4", "pie": "--", "team_logo": "https://cdn.nba.com/logos/nba/1610612737/primary/L/logo.svg"},
{"category": "Assists", "place": 4, "player_name": "Jrue Holiday", "team_name": "BOS", "stat": 8, "player_link": "https://www.nba.com/stats/player/201950/", "photo": "https://cdn.nba.com/headshots/nba/latest/1040x760/201950.png", "ppg": "11.0", "rpg": "4.3", "apg": "3.8", "pie": "--", "team_logo": "https://cdn.nba.com/logos/nba/1610612738/primary/D/logo.svg"},
{"category": "Assists", "place": 3, "player_name": "James Harden", "team_name": "LAC", "stat": 9, "player_link": "https://www.nba.com/stats/player/201935/", "photo": "https://cdn.nba.com/headshots/nba/latest/1040x760/201935.png", "ppg": "22.5", "rpg": "5.9", "apg": "8.7", "pie": "--", "team_logo": "https://cdn.nba.com/logos/nba/1610612746/primary/D/logo.svg"},
{"category": "Assists", "place": 4, "player_name": "Darius Garland", "team_name": "CLE", "stat": 8, "player_link": "https://www.nba.com/stats/player/1629636/", "photo": "https://cdn.nba.com/headshots/nba/latest/1040x760/1629636.png", "ppg": "20.9", "rpg": "2.7", "apg": "6.7", "pie": "--", "team_logo": "https://cdn.nba.com/logos/nba/1610612739/primary/L/logo.svg"},
{"category": "Assists", "place": 2, "player_name": "Jimmy Butler III", "team_name": "GSW", "stat": 10, "player_link": "https://www.nba.com/stats/player/202710/", "photo": "https://cdn.nba.com/headshots/nba/latest/1040x760/202710.png", "ppg": "17.1", "rpg": "5.5", "apg": "5.3", "pie": "--", "team_logo": "https://cdn.nba.com/logos/nba/1610612744/primary/D/logo.svg"},
{"category": "Assists", "place": 1, "player_name": "Donovan Mitchell", "team_name": "CLE", "stat": 11, "player_link": "https://www.nba.com/stats/player/1628378/", "photo": "https://cdn.nba.com/headshots/nba/latest/1040x760/1628378.png", "ppg": "24.1", "rpg": "4.4", "apg": "4.9", "pie": "--", "team_logo": "https://cdn.nba.com/logos/nba/1610612739/primary/L/logo.svg"},
{"category": "Rebounds", "place": 5, "player_name": "Giannis Antetokounmpo", "team_name": "MIL", "stat": 9, "player_link": "https://www.nba.com/stats/player/203507/", "photo": "https://cdn.nba.com/headshots/nba/latest/1040x760/203507.png", "ppg": "30.2", "rpg": "12.0", "apg": "6.0", "pie": "--", "team_logo": "https://cdn.nba.com/logos/nba/1610612749/primary/D/logo.svg"},
{"category": "Rebounds", "place": 3, "player_name": "Draymond Green", "team_name": "GSW", "stat": 10, "player_link": "https://www.nba.com/stats/player/203110/", "photo": "https://cdn.nba.com/headshots/nba/latest/1040x760/203110.png", "ppg": "9.1", "rpg": "6.1", "apg": "5.7", "pie": "--", "team_logo": "https://cdn.nba.com/logos/nba/1610612744/primary/D/logo.svg"},
{"category": "Rebounds", "place": 3, "player_name": "Onyeka Okongwu", "team_name": "ATL", "stat": 10, "player_link": "https://www.nba.com/stats/player/1630168/", "photo": "https://cdn.nba.com/headshots/nba/latest/1040x760/1630168.png", "ppg": "12.9", "rpg": "8.6", "apg": "2.2", "pie": "--", "team_logo": "https://cdn.nba.com/logos/nba/1610612737/primary/L/logo.svg"},
{"category": "Rebounds", "place": 2, "player_name": "Kristaps Porziņģis", "team_name": "BOS", "stat": 13, "player_link": "https://www.nba.com/stats/player/204001/", "photo": "https://cdn.nba.com/headshots/nba/latest/1040x760/204001.png", "ppg": "19.3", "rpg": "6.8", "apg": "1.9", "pie": "--", "team_logo": "https://cdn.nba.com/logos/nba/1610612738/primary/D/logo.svg"},
{"category": "Rebounds", "place": 1, "player_name": "Ivica Zubac", "team_name": "LAC", "stat": 20, "player_link": "https://www.nba.com/stats/player/1627826/", "photo": "https://cdn.nba.com/headshots/nba/latest/1040x760/1627826.png", "ppg": "16.4", "rpg": "12.6", "apg": "2.6", "pie": "--", "team_logo": "https://cdn.nba.com/logos/nba/1610612746/primary/D/logo.svg"},
{"category": "Points", "place": 5, "player_name": "Jimmy Butler III", "team_name": "GSW", "stat": 24, "player_link": "https://www.nba.com/stats/player/202710/", "photo": "https://cdn.nba.com/headshots/nba/latest/1040x760/202710.png", "ppg": "17.1", "rpg": "5.5", "apg": "5.3", "pie": "--", "team_logo": "https://cdn.nba.com/logos/nba/1610612744/primary/D/logo.svg"},
{"category": "Points", "place": 4, "player_name": "Kristaps Porziņģis", "team_name": "BOS", "stat": 25, "player_link": "https://www.nba.com/stats/player/204001/", "photo": "https://cdn.nba.com/headshots/nba/latest/1040x760/204001.png", "ppg": "19.3", "rpg": "6.8", "apg": "1.9", "pie": "--", "team_logo": "https://cdn.nba.com/logos/nba/1610612738/primary/D/logo.svg"}
]