[
{"category": "Points", "place": 4, "player_name": "Kyrie Irving", "team_name": "DAL", "stat": 18, "player_link": "https://www.nba.com/stats/player/202681/", "photo": "https://cdn.nba.com/headshots/nba/latest/1040x760/202681.png", "ppg": "23.8", "rpg": "3.8", "apg": "5.3", "pie": "13.1", "team_logo": "https://cdn.nba.com/logos/nba/1610612742/primary/D/logo.svg"},
{"category": "Points", "place": 3, "player_name": "Santi Aldama", "team_name": "MEM", "stat": 19, "player_link": "https://www.nba.com/stats/player/1630583/", "photo": "https://cdn.nba.com/headshots/nba/latest/1040x760/1630583.png", "ppg": "12.8", "rpg": "6.6", "apg": "3.4", "pie": "12.8", "team_logo": "https://cdn.nba.com/logos/nba/1610612763/primary/D/logo.svg"},
{"category": "Points", "place": 2, "player_name": "Ja Morant", "team_name": "MEM", "stat": 26, "player_link": "https://www.nba.com/stats/player/1629630/", "photo": "https://cdn.nba.com/headshots/nba/latest/1040x760/1629630.png", "ppg": "19.0", "rpg": "3.8", "apg": "8.3", "pie": "14.2", "team_logo": "https://cdn.nba.com/logos/nba/1610612763/primary/D/logo.svg"},
{"category": "Points", "place": 1, "player_name": "Giannis Antetokounmpo", "team_name": "MIL", "stat": 37, "player_link": "https://www.nba.com/stats/player/203507/", "photo": "https://cdn.nba.com/headshots/nba/latest/1040x760/203507.png", "ppg": "28.8", "rpg": "11.8", "apg": "6.3", "pie": "18.2", "team_logo": "https://cdn.nba.com/logos/nba/1610612749/primary/D/logo.svg"},
{"category": "Three Pointers Made", "place": 1, "player_name": "Kyrie Irving", "team_name": "DAL", "stat": 3, "player_link": "https://www.nba.com/stats/player/202681/", "photo": "https://cdn.nba.com/headshots/nba/latest/1040x760/202681.png", "ppg": "23.8", "rpg": "3.8", "apg": "5.3", "pie": "13.1", "team_logo": "https://cdn.nba.com/logos/nba/1610612742/primary/D/logo.svg"},
{"category": "Turnovers", "place": 2, "player_name": "Scotty Pippen Jr.", "team_name": "MEM", "stat": 3, "player_link": "https://www.nba.com/stats/player/1630590/", "photo": "https://cdn.nba.com/headshots/nba/latest/1040x760/1630590.png", "ppg": "9.8", "rpg": "3.0", "apg": "7.4", "pie": "10.0", "team_logo": "https://cdn.nba.com/logos/nba/1610612763/primary/D/logo.svg"},
{"category": "Turnovers", "place": 2, "player_name": "Ja Morant", "team_name": "MEM", "stat": 3, "player_link": "https://www.nba.com/stats/player/1629630/", "photo": "https://cdn.nba.com/headshots/nba/latest/1040x760/1629630.png", "ppg": "19.0", "rpg": "3.8", "apg": "8.3", "pie": "14.2", "team_logo": "https://cdn.nba.com/logos/nba/1610612763/primary/D/logo.svg"},
{"category": "Turnovers", "place": 2, "player_name": "Jaren Jackson Jr.", "team_name": "MEM", "stat": 3, "player_link": "https://www.nba.com/stats/player/1628991/", "photo": "https://cdn.nba.com/headshots/nba/latest/1040x760/1628991.png", "ppg": "20.7", "rpg": "4.7", "apg": "0.7", "pie": "14.6", "team_logo": "https://cdn.nba.com/logos/nba/1610612763/primary/D/logo.svg"},
{"category": "Turnovers", "place": 2, "player_name": "Santi Aldama", "team_name": "MEM", "stat": 3, "player_link": "https://www.nba.com/stats/player/1630583/", "photo": "https://cdn.nba.com/headshots/nba/latest/1040x760/1630583.png", "ppg": "12.8", "rpg": "6.6", "apg": "3.4", "pie": "12.8", "team_logo": "https://cdn.nba.com/logos/nba/1610612763/primary/D/logo.svg"},
{"category": "Steals", "place": 3, "player_name": "Victor Wembanyama", "team_name": "SAS", "stat": 2, "player_link": "https://www.nba.com/stats/player/1641705/", "photo": "https://cdn.nba.com/headshots/nba/latest/1040x760/1641705.png", "ppg": "16.5", "rpg": "11.0", "apg": "2.3", "pie": "13.8", "team_logo": "https://cdn.nba.com/logos/nba/1610612759/primary/D/logo.svg"},
{"category": "Turnovers", "place": 1, "player_name": "Jalen Green", "team_name": "HOU", "stat": 4, "player_link": "https://www.nba.com/stats/player/1630224/", "photo": "https://cdn.nba.com/headshots/nba/latest/1040x760/1630224.png", "ppg": "28.8", "rpg": "3.8", "apg": "2.8", "pie": "14.9", "team_logo": "https://cdn.nba.com/logos/nba/1610612745/alt/logo.svg"},
{"category": "Steals", "place": 3, "player_name": "P.J. Washington", "team_name": "DAL", "stat": 2, "player_link": "https://www.nba.com/stats/player/1629023/", "photo": "https://cdn.nba.com/headshots/nba/latest/1040x760/1629023.png", "ppg": "11.3", "rpg": "7.5", "apg": "1.8", "pie": "8.1", "team_logo": "https://cdn.nba.com/logos/nba/1610612742/primary/D/logo.svg"},
{"category": "Steals", "place": 3, "player_name": "Jake LaRavia", "team_name": "MEM", "stat": 2, "player_link": "https://www.nba.com/stats/player/1631222/", "photo": "https://cdn.nba.com/headshots/nba/latest/1040x760/1631222.png", "ppg": "6.8", "rpg": "6.0", "apg": "3.2", "pie": "7.2", "team_logo": "https://cdn.nba.com/logos/nba/1610612763/primary/D/logo.svg"},
{"category": "Steals", "place": 2, "player_name": "Andre Jackson Jr.", "team_name": "MIL", "stat": 3, "player_link": "https://www.nba.com/stats/player/1641748/", "photo": "https://cdn.nba.com/headshots/nba/latest/1040x760/1641748.png", "ppg": "1.3", "rpg": "1.0", "apg": "1.0", "pie": "10.1", "team_logo": "https://cdn.nba.com/logos/nba/1610612749/primary/D/logo.svg"},
{"category": "Steals", "place": 1, "player_name": "Taurean Prince", "team_name": "MIL", "stat": 4, "player_link": "https://www.nba.com/stats/player/1627752/", "photo": "https://cdn.nba.com/headshots/nba/latest/1040x760/1627752.png", "ppg": "8.3", "rpg": "6.0", "apg": "1.8", "pie": "7.2", "team_logo": "https://cdn.nba.com/logos/nba/1610612749/primary/D/logo.svg"},
{"category": "Blocks", "place": 4, "player_name": "Harrison Barnes", "team_name": "SAS", "stat": 1, "player_link": "https://www.nba.com/stats/player/203084/", "photo": "https://cdn.nba.com/headshots/nba/latest/1040x760/203084.png", "ppg": "12.0", "rpg": "3.5", "apg": "1.0", "pie": "9.5", "team_logo": "https://cdn.nba.com/logos/nba/1610612759/primary/D/logo.svg"},
{"category": "Fantasy Points", "place": 5, "player_name": "Santi Aldama", "team_name": "MEM", "stat": 32.8, "player_link": "https://www.nba.com/stats/player/1630583/", "photo": "https://cdn.nba.com/headshots/nba/latest/1040x760/1630583.png", "ppg": "12.8", "rpg": "6.6", "apg": "3.4", "pie": "12.8", "team_logo": "https://cdn.nba.com/logos/nba/1610612763/primary/D/logo.svg"},
{"category": "Fantasy Points", "place": 4, "player_name": "Victor Wembanyama", "team_name": "SAS", "stat": 35.0, "player_link": "https://www.nba.com/stats/player/1641705/", "photo": "https://cdn.nba.com/headshots/nba/latest/1040x760/1641705.png", "ppg": "16.5", "rpg": "11.0", "apg": "2.3", "pie": "13.8", "team_logo": "https://cdn.nba.com/logos/nba/1610612759/primary/D/logo.svg"},
{"category": "Fantasy Points", "place": 3, "player_name": "Alperen Sengun", "team_name": "HOU", "stat": 37.7, "player_link": "https://www.nba.com/stats/player/1630578/", "photo": "https://cdn.nba.com/headshots/nba/latest/1040x760/1630578.png", "ppg": "14.8", "rpg": "12.5", "apg": "3.5", "pie": "14.9", "team_logo": "https://cdn.nba.com/logos/nba/1610612745/alt/logo.svg"},
{"category": "Fantasy Points", "place": 2, "player_name": "Ja Morant", "team_name": "MEM", "stat": 59.0, "player_link": "https://www.nba.com/stats/player/1629630/", "photo": "https://cdn.nba.com/headshots/nba/latest/1040x760/1629630.png", "ppg": "19.0", "rpg": "3.8", "apg": "8.3", "pie": "14.2", "team_logo": "https://cdn.nba.com/logos/nba/1610612763/primary/D/logo.svg"},
{"category": "Fantasy Points", "place": 1, "player_name": "Giannis Antetokounmpo", "team_name": "MIL", "stat": 61.2, "player_link": "https://www.nba.com/stats/player/203507/", "photo": "https://cdn.nba.com/headshots/nba/latest/1040x760/203507.png", "ppg": "28.8", "rpg": "11.8", "apg": "6.3", "pie": "18.2", "team_logo": "https://cdn.nba.com/logos/nba/1610612749/primary/D/logo.svg"},
{"category": "Free Throws Made", "place": 4, "player_name": "Spencer Dinwiddie", "team_name": "DAL", "stat": 4, "player_link": "https://www.nba.com/stats/player/203915/", "photo": "https://cdn.nba.com/headshots/nba/latest/1040x760/203915.png", "ppg": "4.7", "rpg": "1.0", "apg": "1.0", "pie": "3.6", "team_logo": "https://cdn.nba.com/logos/nba/1610612742/primary/D/logo.svg"},
{"category": "Free Throws Made", "place": 4, "player_name": "Santi Aldama", "team_name": "MEM", "stat": 4, "player_link": "https://www.nba.com/stats/player/1630583/", "photo": "https://cdn.nba.com/headshots/nba/latest/1040x760/1630583.png", "ppg": "12.8", "rpg": "6.6", "apg": "3.4", "pie": "12.8", "team_logo": "https://cdn.nba.com/logos/nba/1610612763/primary/D/logo.svg"},
{"category": "Free Throws Made", "place": 3, "player_name": "Scotty Pippen Jr.", "team_name": "MEM", "stat": 5, "player_link": "https://www.nba.com/stats/player/1630590/", "photo": "https://cdn.nba.com/headshots/nba/latest/1040x760/1630590.png", "ppg": "9.8", "rpg": "3.0", "apg": "7.4", "pie": "10.0", "team_logo": "https://cdn.nba.com/logos/nba/1610612763/primary/D/logo.svg"},
{"category": "Free Throws Made", "place": 2, "player_name": "Ja Morant", "team_name": "MEM", "stat": 6, "player_link": "https://www.nba.com/stats/player/1629630/", "photo": "https://cdn.nba.com/headshots/nba/latest/1040x760/1629630.png", "ppg": "19.0", "rpg": "3.8", "apg": "8.3", "pie": "14.2", "team_logo": "https://cdn.nba.com/logos/nba/1610612763/primary/D/logo.svg"},
{"category": "Free Throws Made", "place": 1, "player_name": "Alperen Sengun", "team_name": "HOU", "stat": 7, "player_link": "https://www.nba.com/stats/player/1630578/", "photo": "https://cdn.nba.com/headshots/nba/latest/1040x760/1630578.png", "ppg": "14.8", "rpg": "12.5", "apg": "3.5", "pie": "14.9", "team_logo": "https://cdn.nba.com/logos/nba/1610612745/alt/logo.svg"},
{"category": "Three Pointers Made", "place": 5, "player_name": "Dillon Brooks", "team_name": "HOU", "stat": 2, "player_link": "https://www.nba.com/stats/player/1628415/", "photo": "https://cdn.nba.com/headshots/nba/latest/1040x760/1628415.png", "ppg": "10.8", "rpg": "4.0", "apg": "0.3", "pie": "4.5", "team_logo": "https://cdn.nba.com/logos/nba/1610612745/alt/logo.svg"},
{"category": "Three Pointers Made", "place": 1, "player_name": "Victor Wembanyama", "team_name": "SAS", "stat": 3, "player_link": "https://www.nba.com/stats/player/1641705/", "photo": "https://cdn.nba.com/headshots/nba/latest/1040x760/1641705.png", "ppg": "16.5", "rpg": "11.0", "apg": "2.3", "pie": "13.8", "team_logo": "https://cdn.nba.com/logos/nba/1610612759/primary/D/logo.svg"},
{"category": "Three Pointers Made", "place": 1, "player_name": "Patty Mills", "team_name": "UTA", "stat": 3, "player_link": "https://www.nba.com/stats/player/201988/", "photo": "https://cdn.nba.com/headshots/nba/latest/1040x760/201988.png", "ppg": "1.8", "rpg": "0.8", "apg": "0.8", "pie": "2.3", "team_logo": "https://cdn.nba.com/logos/nba/1610612762/primary/D/logo.svg"},
{"category": "Three Pointers Made", "place": 1, "player_name": "Brook Lopez", "team_name": "MIL", "stat": 3, "player_link": "https://www.nba.com/stats/player/201572/", "photo": "https://cdn.nba.com/headshots/nba/latest/1040x760/201572.png", "ppg": "11.3", "rpg": "5.5", "apg": "1.8", "pie": "6.5", "team_logo": "https://cdn.nba.com/logos/nba/1610612749/primary/D/logo.svg"},
{"category": "Blocks", "place": 4, "player_name": "Giannis Antetokounmpo", "team_name": "MIL", "stat": 1, "player_link": "https://www.nba.com/stats/player/203507/", "photo": "https://cdn.nba.com/headshots/nba/latest/1040x760/203507.png", "ppg": "28.8", "rpg": "11.8", "apg": "6.3", "pie": "18.2", "team_logo": "https://cdn.nba.com/logos/nba/1610612749/primary/D/logo.svg"},
{"category": "Blocks", "place": 1, "player_name": "Victor Wembanyama", "team_name": "SAS", "stat": 2, "player_link": "https://www.nba.com/stats/player/1641705/", "photo": "https://cdn.nba.com/headshots/nba/latest/1040x760/1641705.png", "ppg": "16.5", "rpg": "11.0", "apg": "2.3", "pie": "13.8", "team_logo": "https://cdn.nba.com/logos/nba/1610612759/primary/D/logo.svg"},
{"category": "Blocks", "place": 1, "player_name": "Daniel Gafford", "team_name": "DAL", "stat": 2, "player_link": "https://www.nba.com/stats/player/1629655/", "photo": "https://cdn.nba.com/headshots/nba/latest/1040x760/1629655.png", "ppg": "9.8", "rpg": "6.3", "apg": "1.8", "pie": "12.9", "team_logo": "https://cdn.nba.com/logos/nba/1610612742/primary/D/logo.svg"},
{"category": "Blocks", "place": 1, "player_name": "Drew Eubanks", "team_name": "UTA", "stat": 2, "player_link": "https://www.nba.com/stats/player/1629234/", "photo": "https://cdn.nba.com/headshots/nba/latest/1040x760/1629234.png", "ppg": "2.0", "rpg": "1.5", "apg": "1.5", "pie": "25.0", "team_logo": "https://cdn.nba.com/logos/nba/1610612762/primary/D/logo.svg"},
{"category": "Assists", "place": 4, "player_name": "Jalen Green", "team_name": "HOU", "stat": 4, "player_link": "https://www.nba.com/stats/player/1630224/", "photo": "https://cdn.nba.com/headshots/nba/latest/1040x760/1630224.png", "ppg": "28.8", "rpg": "3.8", "apg": "2.8", "pie": "14.9", "team_logo": "https://cdn.nba.com/logos/nba/1610612745/alt/logo.svg"},
{"category": "Assists", "place": 4, "player_name": "Giannis Antetokounmpo", "team_name": "MIL", "stat": 4, "player_link": "https://www.nba.com/stats/player/203507/", "photo": "https://cdn.nba.com/headshots/nba/latest/1040x760/203507.png", "ppg": "28.8", "rpg": "11.8", "apg": "6.3", "pie": "18.2", "team_logo": "https://cdn.nba.com/logos/nba/1610612749/primary/D/logo.svg"},
{"category": "Assists", "place": 3, "player_name": "Damian Lillard", "team_name": "MIL", "stat": 6, "player_link": "https://www.nba.com/stats/player/203081/", "photo": "https://cdn.nba.com/headshots/nba/latest/1040x760/203081.png", "ppg": "28.0", "rpg": "6.0", "apg": "6.3", "pie": "16.6", "team_logo": "https://cdn.nba.com/logos/nba/1610612749/primary/D/logo.svg"},
{"category": "Assists", "place": 2, "player_name": "Chris Paul", "team_name": "SAS", "stat": 7, "player_link": "https://www.nba.com/stats/player/101108/", "photo": "https://cdn.nba.com/headshots/nba/latest/1040x760/101108.png", "ppg": "9.0", "rpg": "3.3", "apg": "7.3", "pie": "9.3", "team_logo": "https://cdn.nba.com/logos/nba/1610612759/primary/D/logo.svg"},
{"category": "Assists", "place": 1, "player_name": "Ja Morant", "team_name": "MEM", "stat": 14, "player_link": "https://www.nba.com/stats/player/1629630/", "photo": "https://cdn.nba.com/headshots/nba/latest/1040x760/1629630.png", "ppg": "19.0", "rpg": "3.8", "apg": "8.3", "pie": "14.2", "team_logo": "https://cdn.nba.com/logos/nba/1610612763/primary/D/logo.svg"},
{"category": "Rebounds", "place": 5, "player_name": "Santi Aldama", "team_name": "MEM", "stat": 9, "player_link": "https://www.nba.com/stats/player/1630583/", "photo": "https://cdn.nba.com/headshots/nba/latest/1040x760/1630583.png", "ppg": "12.8", "rpg": "6.6", "apg": "3.4", "pie": "12.8", "team_logo": "https://cdn.nba.com/logos/nba/1610612763/primary/D/logo.svg"},
{"category": "Rebounds", "place": 3, "player_name": "Ja Morant", "team_name": "MEM", "stat": 10, "player_link": "https://www.nba.com/stats/player/1629630/", "photo": "https://cdn.nba.com/headshots/nba/latest/1040x760/1629630.png", "ppg": "19.0", "rpg": "3.8", "apg": "8.3", "pie": "14.2", "team_logo": "https://cdn.nba.com/logos/nba/1610612763/primary/D/logo.svg"},
{"category": "Rebounds", "place": 3, "player_name": "Jake LaRavia", "team_name": "MEM", "stat": 10, "player_link": "https://www.nba.com/stats/player/1631222/", "photo": "https://cdn.nba.com/headshots/nba/latest/1040x760/1631222.png", "ppg": "6.8", "rpg": "6.0", "apg": "3.2", "pie": "7.2", "team_logo": "https://cdn.nba.com/logos/nba/1610612763/primary/D/logo.svg"},
{"category": "Rebounds", "place": 1, "player_name": "Alperen Sengun", "team_name": "HOU", "stat": 11, "player_link": "https://www.nba.com/stats/player/1630578/", "photo": "https://cdn.nba.com/headshots/nba/latest/1040x760/1630578.png", "ppg": "14.8", "rpg": "12.5", "apg": "3.5", "pie": "14.9", "team_logo": "https://cdn.nba.com/logos/nba/1610612745/alt/logo.svg"},
{"category": "Rebounds", "place": 1, "player_name": "Giannis Antetokounmpo", "team_name": "MIL", "stat": 11, "player_link": "https://www.nba.com/stats/player/203507/", "photo": "https://cdn.nba.com/headshots/nba/latest/1040x760/203507.png", "ppg": "28.8", "rpg": "11.8", "apg": "6.3", "pie": "18.2", "team_logo": "https://cdn.nba.com/logos/nba/1610612749/primary/D/logo.svg"},
{"category": "Points", "place": 5, "player_name": "Alperen Sengun", "team_name": "HOU", "stat": 17, "player_link": "https://www.nba.com/stats/player/1630578/", "photo": "https://cdn.nba.com/headshots/nba/latest/1040x760/1630578.png", "ppg": "14.8", "rpg": "12.5", "apg": "3.5", "pie": "14.9", "team_logo": "https://cdn.nba.com/logos/nba/1610612745/alt/logo.svg"}
]