[
{"category": "Points", "place": 4, "player_name": "Zach LaVine", "team_name": "CHI", "stat": 30, "player_link": "https://www.nba.com/stats/player/203897/", "photo": "https://cdn.nba.com/headshots/nba/latest/1040x760/203897.png", "ppg": "22.1", "rpg": "4.4", "apg": "4.2", "pie": "10.9", "team_logo": "https://cdn.nba.com/logos/nba/1610612741/primary/D/logo.svg"},
{"category": "Points", "place": 1, "player_name": "Dennis Schröder", "team_name": "BKN", "stat": 34, "player_link": "https://www.nba.com/stats/player/203471/", "photo": "https://cdn.nba.com/headshots/nba/latest/1040x760/203471.png", "ppg": "18.6", "rpg": "3.0", "apg": "6.5", "pie": "11.4", "team_logo": "https://cdn.nba.com/logos/nba/1610612751/primary/D/logo.svg"},
{"category": "Points", "place": 3, "player_name": "Joel Embiid", "team_name": "PHI", "stat": 31, "player_link": "https://www.nba.com/stats/player/203954/", "photo": "https://cdn.nba.com/headshots/nba/latest/1040x760/203954.png", "ppg": "22.0", "rpg": "8.4", "apg": "3.6", "pie": "14.5", "team_logo": "https://cdn.nba.com/logos/nba/1610612755/alt/logo.svg"},
{"category": "Points", "place": 1, "player_name": "Giannis Antetokounmpo", "team_name": "MIL", "stat": 34, "player_link": "https://www.nba.com/stats/player/203507/", "photo": "https://cdn.nba.com/headshots/nba/latest/1040x760/203507.png", "ppg": "32.5", "rpg": "11.6", "apg": "6.2", "pie": "21.0", "team_logo": "https://cdn.nba.com/logos/nba/1610612749/primary/D/logo.svg"},
{"category": "Turnovers", "place": 5, "player_name": "Giannis Antetokounmpo", "team_name": "MIL", "stat": 3, "player_link": "https://www.nba.com/stats/player/203507/", "photo": "https://cdn.nba.com/headshots/nba/latest/1040x760/203507.png", "ppg": "32.5", "rpg": "11.6", "apg": "6.2", "pie": "21.0", "team_logo": "https://cdn.nba.com/logos/nba/1610612749/primary/D/logo.svg"},
{"category": "Turnovers", "place": 4, "player_name": "Josh Giddey", "team_name": "CHI", "stat": 4, "player_link": "https://www.nba.com/stats/player/1630581/", "photo": "https://cdn.nba.com/headshots/nba/latest/1040x760/1630581.png", "ppg": "11.7", "rpg": "6.2", "apg": "6.9", "pie": "11.0", "team_logo": "https://cdn.nba.com/logos/nba/1610612741/primary/D/logo.svg"},
{"category": "Turnovers", "place": 3, "player_name": "Zach LaVine", "team_name": "CHI", "stat": 5, "player_link": "https://www.nba.com/stats/player/203897/", "photo": "https://cdn.nba.com/headshots/nba/latest/1040x760/203897.png", "ppg": "22.1", "rpg": "4.4", "apg": "4.2", "pie": "10.9", "team_logo": "https://cdn.nba.com/logos/nba/1610612741/primary/D/logo.svg"},
{"category": "Turnovers", "place": 1, "player_name": "Damian Lillard", "team_name": "MIL", "stat": 7, "player_link": "https://www.nba.com/stats/player/203081/", "photo": "https://cdn.nba.com/headshots/nba/latest/1040x760/203081.png", "ppg": "25.7", "rpg": "4.6", "apg": "7.5", "pie": "14.8", "team_logo": "https://cdn.nba.com/logos/nba/1610612749/primary/D/logo.svg"},
{"category": "Turnovers", "place": 2, "player_name": "Joel Embiid", "team_name": "PHI", "stat": 6, "player_link": "https://www.nba.com/stats/player/203954/", "photo": "https://cdn.nba.com/headshots/nba/latest/1040x760/203954.png", "ppg": "22.0", "rpg": "8.4", "apg": "3.6", "pie": "14.5", "team_logo": "https://cdn.nba.com/logos/nba/1610612755/alt/logo.svg"},
{"category": "Steals", "place": 5, "player_name": "Josh Giddey", "team_name": "CHI", "stat": 2, "player_link": "https://www.nba.com/stats/player/1630581/", "photo": "https://cdn.nba.com/headshots/nba/latest/1040x760/1630581.png", "ppg": "11.7", "rpg": "6.2", "apg": "6.9", "pie": "11.0", "team_logo": "https://cdn.nba.com/logos/nba/1610612741/primary/D/logo.svg"},
{"category": "Steals", "place": 2, "player_name": "Kelly Oubre Jr.", "team_name": "PHI", "stat": 3, "player_link": "https://www.nba.com/stats/player/1626162/", "photo": "https://cdn.nba.com/headshots/nba/latest/1040x760/1626162.png", "ppg": "12.9", "rpg": "5.3", "apg": "1.4", "pie": "7.6", "team_logo": "https://cdn.nba.com/logos/nba/1610612755/alt/logo.svg"},
{"category": "Steals", "place": 2, "player_name": "Jared McCain", "team_name": "PHI", "stat": 3, "player_link": "https://www.nba.com/stats/player/1642272/", "photo": "https://cdn.nba.com/headshots/nba/latest/1040x760/1642272.png", "ppg": "15.8", "rpg": "2.5", "apg": "2.6", "pie": "11.3", "team_logo": "https://cdn.nba.com/logos/nba/1610612755/alt/logo.svg"},
{"category": "Steals", "place": 2, "player_name": "Nic Claxton", "team_name": "BKN", "stat": 3, "player_link": "https://www.nba.com/stats/player/1629651/", "photo": "https://cdn.nba.com/headshots/nba/latest/1040x760/1629651.png", "ppg": "9.8", "rpg": "7.8", "apg": "2.3", "pie": "13.2", "team_logo": "https://cdn.nba.com/logos/nba/1610612751/primary/D/logo.svg"},
{"category": "Steals", "place": 1, "player_name": "Nikola Vučević", "team_name": "CHI", "stat": 4, "player_link": "https://www.nba.com/stats/player/202696/", "photo": "https://cdn.nba.com/headshots/nba/latest/1040x760/202696.png", "ppg": "21.0", "rpg": "9.8", "apg": "3.2", "pie": "14.8", "team_logo": "https://cdn.nba.com/logos/nba/1610612741/primary/D/logo.svg"},
{"category": "Blocks", "place": 3, "player_name": "T.J. McConnell", "team_name": "IND", "stat": 2, "player_link": "https://www.nba.com/stats/player/204456/", "photo": "https://cdn.nba.com/headshots/nba/latest/1040x760/204456.png", "ppg": "11.5", "rpg": "2.5", "apg": "4.0", "pie": "13.8", "team_logo": "https://cdn.nba.com/logos/nba/1610612754/primary/D/logo.svg"},
{"category": "Blocks", "place": 3, "player_name": "Joel Embiid", "team_name": "PHI", "stat": 2, "player_link": "https://www.nba.com/stats/player/203954/", "photo": "https://cdn.nba.com/headshots/nba/latest/1040x760/203954.png", "ppg": "22.0", "rpg": "8.4", "apg": "3.6", "pie": "14.5", "team_logo": "https://cdn.nba.com/logos/nba/1610612755/alt/logo.svg"},
{"category": "Fantasy Points", "place": 5, "player_name": "Joel Embiid", "team_name": "PHI", "stat": 51.4, "player_link": "https://www.nba.com/stats/player/203954/", "photo": "https://cdn.nba.com/headshots/nba/latest/1040x760/203954.png", "ppg": "22.0", "rpg": "8.4", "apg": "3.6", "pie": "14.5", "team_logo": "https://cdn.nba.com/logos/nba/1610612755/alt/logo.svg"},
{"category": "Fantasy Points", "place": 3, "player_name": "Dennis Schröder", "team_name": "BKN", "stat": 54.1, "player_link": "https://www.nba.com/stats/player/203471/", "photo": "https://cdn.nba.com/headshots/nba/latest/1040x760/203471.png", "ppg": "18.6", "rpg": "3.0", "apg": "6.5", "pie": "11.4", "team_logo": "https://cdn.nba.com/logos/nba/1610612751/primary/D/logo.svg"},
{"category": "Fantasy Points", "place": 4, "player_name": "Nic Claxton", "team_name": "BKN", "stat": 54.0, "player_link": "https://www.nba.com/stats/player/1629651/", "photo": "https://cdn.nba.com/headshots/nba/latest/1040x760/1629651.png", "ppg": "9.8", "rpg": "7.8", "apg": "2.3", "pie": "13.2", "team_logo": "https://cdn.nba.com/logos/nba/1610612751/primary/D/logo.svg"},
{"category": "Fantasy Points", "place": 2, "player_name": "Tyrese Maxey", "team_name": "PHI", "stat": 59.2, "player_link": "https://www.nba.com/stats/player/1630178/", "photo": "https://cdn.nba.com/headshots/nba/latest/1040x760/1630178.png", "ppg": "24.3", "rpg": "3.6", "apg": "5.2", "pie": "12.7", "team_logo": "https://cdn.nba.com/logos/nba/1610612755/alt/logo.svg"},
{"category": "Fantasy Points", "place": 1, "player_name": "Giannis Antetokounmpo", "team_name": "MIL", "stat": 62.2, "player_link": "https://www.nba.com/stats/player/203507/", "photo": "https://cdn.nba.com/headshots/nba/latest/1040x760/203507.png", "ppg": "32.5", "rpg": "11.6", "apg": "6.2", "pie": "21.0", "team_logo": "https://cdn.nba.com/logos/nba/1610612749/primary/D/logo.svg"},
{"category": "Free Throws Made", "place": 5, "player_name": "Cameron Johnson", "team_name": "BKN", "stat": 4, "player_link": "https://www.nba.com/stats/player/1629661/", "photo": "https://cdn.nba.com/headshots/nba/latest/1040x760/1629661.png", "ppg": "18.8", "rpg": "4.3", "apg": "2.9", "pie": "12.5", "team_logo": "https://cdn.nba.com/logos/nba/1610612751/primary/D/logo.svg"},
{"category": "Free Throws Made", "place": 3, "player_name": "Gary Trent Jr.", "team_name": "MIL", "stat": 5, "player_link": "https://www.nba.com/stats/player/1629018/", "photo": "https://cdn.nba.com/headshots/nba/latest/1040x760/1629018.png", "ppg": "9.4", "rpg": "2.1", "apg": "1.0", "pie": "5.2", "team_logo": "https://cdn.nba.com/logos/nba/1610612749/primary/D/logo.svg"},
{"category": "Free Throws Made", "place": 3, "player_name": "Joel Embiid", "team_name": "PHI", "stat": 5, "player_link": "https://www.nba.com/stats/player/203954/", "photo": "https://cdn.nba.com/headshots/nba/latest/1040x760/203954.png", "ppg": "22.0", "rpg": "8.4", "apg": "3.6", "pie": "14.5", "team_logo": "https://cdn.nba.com/logos/nba/1610612755/alt/logo.svg"},
{"category": "Free Throws Made", "place": 2, "player_name": "Giannis Antetokounmpo", "team_name": "MIL", "stat": 6, "player_link": "https://www.nba.com/stats/player/203507/", "photo": "https://cdn.nba.com/headshots/nba/latest/1040x760/203507.png", "ppg": "32.5", "rpg": "11.6", "apg": "6.2", "pie": "21.0", "team_logo": "https://cdn.nba.com/logos/nba/1610612749/primary/D/logo.svg"},
{"category": "Free Throws Made", "place": 1, "player_name": "Damian Lillard", "team_name": "MIL", "stat": 9, "player_link": "https://www.nba.com/stats/player/203081/", "photo": "https://cdn.nba.com/headshots/nba/latest/1040x760/203081.png", "ppg": "25.7", "rpg": "4.6", "apg": "7.5", "pie": "14.8", "team_logo": "https://cdn.nba.com/logos/nba/1610612749/primary/D/logo.svg"},
{"category": "Three Pointers Made", "place": 5, "player_name": "Dorian Finney-Smith", "team_name": "BKN", "stat": 3, "player_link": "https://www.nba.com/stats/player/1627827/", "photo": "https://cdn.nba.com/headshots/nba/latest/1040x760/1627827.png", "ppg": "10.6", "rpg": "4.3", "apg": "1.8", "pie": "6.6", "team_logo": "https://cdn.nba.com/logos/nba/1610612751/primary/D/logo.svg"},
{"category": "Three Pointers Made", "place": 3, "player_name": "Dennis Schröder", "team_name": "BKN", "stat": 4, "player_link": "https://www.nba.com/stats/player/203471/", "photo": "https://cdn.nba.com/headshots/nba/latest/1040x760/203471.png", "ppg": "18.6", "rpg": "3.0", "apg": "6.5", "pie": "11.4", "team_logo": "https://cdn.nba.com/logos/nba/1610612751/primary/D/logo.svg"},
{"category": "Three Pointers Made", "place": 3, "player_name": "Cameron Johnson", "team_name": "BKN", "stat": 4, "player_link": "https://www.nba.com/stats/player/1629661/", "photo": "https://cdn.nba.com/headshots/nba/latest/1040x760/1629661.png", "ppg": "18.8", "rpg": "4.3", "apg": "2.9", "pie": "12.5", "team_logo": "https://cdn.nba.com/logos/nba/1610612751/primary/D/logo.svg"},
{"category": "Three Pointers Made", "place": 1, "player_name": "Zach LaVine", "team_name": "CHI", "stat": 6, "player_link": "https://www.nba.com/stats/player/203897/", "photo": "https://cdn.nba.com/headshots/nba/latest/1040x760/203897.png", "ppg": "22.1", "rpg": "4.4", "apg": "4.2", "pie": "10.9", "team_logo": "https://cdn.nba.com/logos/nba/1610612741/primary/D/logo.svg"},
{"category": "Three Pointers Made", "place": 2, "player_name": "Bobby Portis", "team_name": "MIL", "stat": 5, "player_link": "https://www.nba.com/stats/player/1626171/", "photo": "https://cdn.nba.com/headshots/nba/latest/1040x760/1626171.png", "ppg": "12.8", "rpg": "7.5", "apg": "1.5", "pie": "12.4", "team_logo": "https://cdn.nba.com/logos/nba/1610612749/primary/D/logo.svg"},
{"category": "Blocks", "place": 3, "player_name": "Nic Claxton", "team_name": "BKN", "stat": 2, "player_link": "https://www.nba.com/stats/player/1629651/", "photo": "https://cdn.nba.com/headshots/nba/latest/1040x760/1629651.png", "ppg": "9.8", "rpg": "7.8", "apg": "2.3", "pie": "13.2", "team_logo": "https://cdn.nba.com/logos/nba/1610612751/primary/D/logo.svg"},
{"category": "Blocks", "place": 1, "player_name": "Bobby Portis", "team_name": "MIL", "stat": 3, "player_link": "https://www.nba.com/stats/player/1626171/", "photo": "https://cdn.nba.com/headshots/nba/latest/1040x760/1626171.png", "ppg": "12.8", "rpg": "7.5", "apg": "1.5", "pie": "12.4", "team_logo": "https://cdn.nba.com/logos/nba/1610612749/primary/D/logo.svg"},
{"category": "Blocks", "place": 1, "player_name": "Giannis Antetokounmpo", "team_name": "MIL", "stat": 3, "player_link": "https://www.nba.com/stats/player/203507/", "photo": "https://cdn.nba.com/headshots/nba/latest/1040x760/203507.png", "ppg": "32.5", "rpg": "11.6", "apg": "6.2", "pie": "21.0", "team_logo": "https://cdn.nba.com/logos/nba/1610612749/primary/D/logo.svg"},
{"category": "Assists", "place": 5, "player_name": "Khris Middleton", "team_name": "MIL", "stat": 6, "player_link": "https://www.nba.com/stats/player/203114/", "photo": "https://cdn.nba.com/headshots/nba/latest/1040x760/203114.png", "ppg": "11.0", "rpg": "2.5", "apg": "5.5", "pie": "10.3", "team_logo": "https://cdn.nba.com/logos/nba/1610612749/primary/D/logo.svg"},
{"category": "Assists", "place": 2, "player_name": "Dennis Schröder", "team_name": "BKN", "stat": 11, "player_link": "https://www.nba.com/stats/player/203471/", "photo": "https://cdn.nba.com/headshots/nba/latest/1040x760/203471.png", "ppg": "18.6", "rpg": "3.0", "apg": "6.5", "pie": "11.4", "team_logo": "https://cdn.nba.com/logos/nba/1610612751/primary/D/logo.svg"},
{"category": "Assists", "place": 2, "player_name": "Damian Lillard", "team_name": "MIL", "stat": 11, "player_link": "https://www.nba.com/stats/player/203081/", "photo": "https://cdn.nba.com/headshots/nba/latest/1040x760/203081.png", "ppg": "25.7", "rpg": "4.6", "apg": "7.5", "pie": "14.8", "team_logo": "https://cdn.nba.com/logos/nba/1610612749/primary/D/logo.svg"},
{"category": "Assists", "place": 2, "player_name": "Josh Giddey", "team_name": "CHI", "stat": 11, "player_link": "https://www.nba.com/stats/player/1630581/", "photo": "https://cdn.nba.com/headshots/nba/latest/1040x760/1630581.png", "ppg": "11.7", "rpg": "6.2", "apg": "6.9", "pie": "11.0", "team_logo": "https://cdn.nba.com/logos/nba/1610612741/primary/D/logo.svg"},
{"category": "Rebounds", "place": 4, "player_name": "Kelly Oubre Jr.", "team_name": "PHI", "stat": 10, "player_link": "https://www.nba.com/stats/player/1626162/", "photo": "https://cdn.nba.com/headshots/nba/latest/1040x760/1626162.png", "ppg": "12.9", "rpg": "5.3", "apg": "1.4", "pie": "7.6", "team_logo": "https://cdn.nba.com/logos/nba/1610612755/alt/logo.svg"},
{"category": "Assists", "place": 1, "player_name": "Tyrese Maxey", "team_name": "PHI", "stat": 14, "player_link": "https://www.nba.com/stats/player/1630178/", "photo": "https://cdn.nba.com/headshots/nba/latest/1040x760/1630178.png", "ppg": "24.3", "rpg": "3.6", "apg": "5.2", "pie": "12.7", "team_logo": "https://cdn.nba.com/logos/nba/1610612755/alt/logo.svg"},
{"category": "Rebounds", "place": 4, "player_name": "Nic Claxton", "team_name": "BKN", "stat": 10, "player_link": "https://www.nba.com/stats/player/1629651/", "photo": "https://cdn.nba.com/headshots/nba/latest/1040x760/1629651.png", "ppg": "9.8", "rpg": "7.8", "apg": "2.3", "pie": "13.2", "team_logo": "https://cdn.nba.com/logos/nba/1610612751/primary/D/logo.svg"},
{"category": "Rebounds", "place": 2, "player_name": "Giannis Antetokounmpo", "team_name": "MIL", "stat": 11, "player_link": "https://www.nba.com/stats/player/203507/", "photo": "https://cdn.nba.com/headshots/nba/latest/1040x760/203507.png", "ppg": "32.5", "rpg": "11.6", "apg": "6.2", "pie": "21.0", "team_logo": "https://cdn.nba.com/logos/nba/1610612749/primary/D/logo.svg"},
{"category": "Rebounds", "place": 2, "player_name": "Tyrese Maxey", "team_name": "PHI", "stat": 11, "player_link": "https://www.nba.com/stats/player/1630178/", "photo": "https://cdn.nba.com/headshots/nba/latest/1040x760/1630178.png", "ppg": "24.3", "rpg": "3.6", "apg": "5.2", "pie": "12.7", "team_logo": "https://cdn.nba.com/logos/nba/1610612755/alt/logo.svg"},
{"category": "Points", "place": 5, "player_name": "Cameron Johnson", "team_name": "BKN", "stat": 26, "player_link": "https://www.nba.com/stats/player/1629661/", "photo": "https://cdn.nba.com/headshots/nba/latest/1040x760/1629661.png", "ppg": "18.8", "rpg": "4.3", "apg": "2.9", "pie": "12.5", "team_logo": "https://cdn.nba.com/logos/nba/1610612751/primary/D/logo.svg"},
{"category": "Rebounds", "place": 1, "player_name": "Joel Embiid", "team_name": "PHI", "stat": 12, "player_link": "https://www.nba.com/stats/player/203954/", "photo": "https://cdn.nba.com/headshots/nba/latest/1040x760/203954.png", "ppg": "22.0", "rpg": "8.4", "apg": "3.6", "pie": "14.5", "team_logo": "https://cdn.nba.com/logos/nba/1610612755/alt/logo.svg"}
]