[
{"category": "Points", "place": 1, "player_name": "Tobias Harris", "team_name": "PHI", "stat": 11},
{"category": "Points", "place": 1, "player_name": "Naji Marshall", "team_name": "NOP", "stat": 11},
{"category": "Points", "place": 1, "player_name": "Zion Williamson", "team_name": "NOP", "stat": 11},
{"category": "Points", "place": 4, "player_name": "Buddy Boeheim", "team_name": "DET", "stat": 8},
{"category": "Points", "place": 4, "player_name": "James Harden", "team_name": "LAC", "stat": 8},
{"category": "Rebounds", "place": 1, "player_name": "Mo Bamba", "team_name": "PHI", "stat": 7},
{"category": "Rebounds", "place": 2, "player_name": "Tosan Evbuomwan", "team_name": "DET", "stat": 5},
{"category": "Rebounds", "place": 2, "player_name": "James Wiseman", "team_name": "DET", "stat": 5},
{"category": "Rebounds", "place": 4, "player_name": "Jonas Valanciunas", "team_name": "NOP", "stat": 4},
{"category": "Rebounds", "place": 4, "player_name": "Ivica Zubac", "team_name": "LAC", "stat": 4},
{"category": "Assists", "place": 1, "player_name": "Marcus Sasser", "team_name": "DET", "stat": 4},
{"category": "Assists", "place": 2, "player_name": "Tyrese Maxey", "team_name": "PHI", "stat": 3},
{"category": "Assists", "place": 2, "player_name": "Zion Williamson", "team_name": "NOP", "stat": 3},
{"category": "Assists", "place": 4, "player_name": "Jordan Hawkins", "team_name": "NOP", "stat": 2},
{"category": "Assists", "place": 4, "player_name": "Buddy Hield", "team_name": "PHI", "stat": 2},
{"category": "Blocks", "place": 1, "player_name": "Mo Bamba", "team_name": "PHI", "stat": 2},
{"category": "Blocks", "place": 1, "player_name": "Trey Murphy III", "team_name": "NOP", "stat": 2},
{"category": "Blocks", "place": 3, "player_name": "Tosan Evbuomwan", "team_name": "DET", "stat": 1},
{"category": "Blocks", "place": 3, "player_name": "Jonas Valanciunas", "team_name": "NOP", "stat": 1},
{"category": "Blocks", "place": 3, "player_name": "Ivica Zubac", "team_name": "LAC", "stat": 1},
{"category": "Steals", "place": 1, "player_name": "Herbert Jones", "team_name": "NOP", "stat": 2},
{"category": "Steals", "place": 1, "player_name": "Marcus Sasser", "team_name": "DET", "stat": 2},
{"category": "Steals", "place": 3, "player_name": "Naji Marshall", "team_name": "NOP", "stat": 1},
{"category": "Steals", "place": 3, "player_name": "CJ McCollum", "team_name": "NOP", "stat": 1},
{"category": "Steals", "place": 3, "player_name": "Chimezie Metu", "team_name": "DET", "stat": 1},
{"category": "Turnovers", "place": 1, "player_name": "Jaden Ivey", "team_name": "DET", "stat": 3},
{"category": "Turnovers", "place": 1, "player_name": "Zion Williamson", "team_name": "NOP", "stat": 3},
{"category": "Turnovers", "place": 3, "player_name": "Tobias Harris", "team_name": "PHI", "stat": 2},
{"category": "Turnovers", "place": 3, "player_name": "Herbert Jones", "team_name": "NOP", "stat": 2},
{"category": "Turnovers", "place": 3, "player_name": "Marcus Sasser", "team_name": "DET", "stat": 2},
{"category": "Three Pointers Made", "place": 1, "player_name": "Naji Marshall", "team_name": "NOP", "stat": 3},
{"category": "Three Pointers Made", "place": 2, "player_name": "Buddy Boeheim", "team_name": "DET", "stat": 2},
{"category": "Three Pointers Made", "place": 2, "player_name": "Jaden Ivey", "team_name": "DET", "stat": 2},
{"category": "Three Pointers Made", "place": 2, "player_name": "Terance Mann", "team_name": "LAC", "stat": 2},
{"category": "Three Pointers Made", "place": 2, "player_name": "Kelly Oubre Jr.", "team_name": "PHI", "stat": 2},
{"category": "Free Throws Made", "place": 1, "player_name": "Zion Williamson", "team_name": "NOP", "stat": 3},
{"category": "Free Throws Made", "place": 2, "player_name": "Buddy Boeheim", "team_name": "DET", "stat": 2},
{"category": "Free Throws Made", "place": 2, "player_name": "James Harden", "team_name": "LAC", "stat": 2},
{"category": "Free Throws Made", "place": 2, "player_name": "Chimezie Metu", "team_name": "DET", "stat": 2},
{"category": "Free Throws Made", "place": 2, "player_name": "Trey Murphy III", "team_name": "NOP", "stat": 2},
{"category": "Fantasy Points", "place": 1, "player_name": "Naji Marshall", "team_name": "NOP", "stat": 20.6},
{"category": "Fantasy Points", "place": 2, "player_name": "Mo Bamba", "team_name": "PHI", "stat": 18.9},
{"category": "Fantasy Points", "place": 3, "player_name": "Trey Murphy III", "team_name": "NOP", "stat": 18.6},
{"category": "Fantasy Points", "place": 4, "player_name": "Jonas Valanciunas", "team_name": "NOP", "stat": 15.8},
{"category": "Fantasy Points", "place": 5, "player_name": "Zion Williamson", "team_name": "NOP", "stat": 14.9}
]